{
"meta":{"test_sets":[],"test_metrics":[],"learn_metrics":[{"best_value":"Min","name":"RMSE"}],"launch_mode":"Train","parameters":"","iteration_count":1000,"learn_sets":["learn"],"name":"experiment"},
"iterations":[
{"learn":[14.59871775],"iteration":0,"passed_time":0.001826287268,"remaining_time":1.824460981},
{"learn":[14.22518863],"iteration":1,"passed_time":0.004503042039,"remaining_time":2.247017977},
{"learn":[13.8866124],"iteration":2,"passed_time":0.005624513803,"remaining_time":1.869213421},
{"learn":[13.52356875],"iteration":3,"passed_time":0.00662378362,"remaining_time":1.649322121},
{"learn":[13.18870211],"iteration":4,"passed_time":0.007604334414,"remaining_time":1.513262548},
{"learn":[12.9124226],"iteration":5,"passed_time":0.008531487718,"remaining_time":1.413383132},
{"learn":[12.60003351],"iteration":6,"passed_time":0.009218792523,"remaining_time":1.307751568},
{"learn":[12.32990573],"iteration":7,"passed_time":0.009881162159,"remaining_time":1.225264108},
{"learn":[12.0660619],"iteration":8,"passed_time":0.0105544484,"remaining_time":1.16216204},
{"learn":[11.77309809],"iteration":9,"passed_time":0.01119943906,"remaining_time":1.108744467},
{"learn":[11.49227636],"iteration":10,"passed_time":0.01185351439,"remaining_time":1.065738703},
{"learn":[11.26264833],"iteration":11,"passed_time":0.01248889348,"remaining_time":1.02825223},
{"learn":[11.04260393],"iteration":12,"passed_time":0.01312100165,"remaining_time":0.9961868178},
{"learn":[10.79916926],"iteration":13,"passed_time":0.0137637802,"remaining_time":0.9693633772},
{"learn":[10.5541002],"iteration":14,"passed_time":0.01438703214,"remaining_time":0.9447484441},
{"learn":[10.31918115],"iteration":15,"passed_time":0.0150230015,"remaining_time":0.9239145925},
{"learn":[10.10004441],"iteration":16,"passed_time":0.01568655334,"remaining_time":0.9070518785},
{"learn":[9.894556723],"iteration":17,"passed_time":0.01631907447,"remaining_time":0.8902961741},
{"learn":[9.690174082],"iteration":18,"passed_time":0.01699846681,"remaining_time":0.8776576811},
{"learn":[9.506034866],"iteration":19,"passed_time":0.0176559359,"remaining_time":0.8651408589},
{"learn":[9.338524633],"iteration":20,"passed_time":0.01864277009,"remaining_time":0.8691081865},
{"learn":[9.170203312],"iteration":21,"passed_time":0.01961981152,"remaining_time":0.8721898028},
{"learn":[9.010299969],"iteration":22,"passed_time":0.02043555498,"remaining_time":0.8680668354},
{"learn":[8.843866678],"iteration":23,"passed_time":0.02106052547,"remaining_time":0.8564613692},
{"learn":[8.690548059],"iteration":24,"passed_time":0.02170326901,"remaining_time":0.8464274913},
{"learn":[8.555307687],"iteration":25,"passed_time":0.02233676058,"remaining_time":0.8367694156},
{"learn":[8.413851302],"iteration":26,"passed_time":0.02297734425,"remaining_time":0.8280354058},
{"learn":[8.29256019],"iteration":27,"passed_time":0.02361121488,"remaining_time":0.8196464595},
{"learn":[8.162193833],"iteration":28,"passed_time":0.02425282235,"remaining_time":0.8120513966},
{"learn":[8.040736294],"iteration":29,"passed_time":0.02489727888,"remaining_time":0.8050120172},
{"learn":[7.921220278],"iteration":30,"passed_time":0.02554183991,"remaining_time":0.7983884796},
{"learn":[7.809589039],"iteration":31,"passed_time":0.02622892683,"remaining_time":0.7934250367},
{"learn":[7.699675801],"iteration":32,"passed_time":0.0269368593,"remaining_time":0.7893316044},
{"learn":[7.60645267],"iteration":33,"passed_time":0.02767549677,"remaining_time":0.7863097024},
{"learn":[7.498880302],"iteration":34,"passed_time":0.02836836965,"remaining_time":0.7821564776},
{"learn":[7.401158744],"iteration":35,"passed_time":0.02899910831,"remaining_time":0.7765316782},
{"learn":[7.306431077],"iteration":36,"passed_time":0.02962105077,"remaining_time":0.770947889},
{"learn":[7.223863468],"iteration":37,"passed_time":0.030283013,"remaining_time":0.7666383818},
{"learn":[7.143477682],"iteration":38,"passed_time":0.03104386107,"remaining_time":0.7649525767},
{"learn":[7.062817131],"iteration":39,"passed_time":0.03169010731,"remaining_time":0.7605625753},
{"learn":[6.990793435],"iteration":40,"passed_time":0.03233712444,"remaining_time":0.7563732278},
{"learn":[6.931862224],"iteration":41,"passed_time":0.03297165148,"remaining_time":0.7520676695},
{"learn":[6.858296558],"iteration":42,"passed_time":0.03385861994,"remaining_time":0.7535511461},
{"learn":[6.786268161],"iteration":43,"passed_time":0.03479057931,"remaining_time":0.755904405},
{"learn":[6.717118549],"iteration":44,"passed_time":0.03555366228,"remaining_time":0.7545277218},
{"learn":[6.652948106],"iteration":45,"passed_time":0.03619458055,"remaining_time":0.750644127},
{"learn":[6.589686076],"iteration":46,"passed_time":0.03685708636,"remaining_time":0.7473362404},
{"learn":[6.531283097],"iteration":47,"passed_time":0.0374965234,"remaining_time":0.7436810473},
{"learn":[6.471368031],"iteration":48,"passed_time":0.03816089949,"remaining_time":0.7406329677},
{"learn":[6.416481395],"iteration":49,"passed_time":0.03879487684,"remaining_time":0.73710266},
{"learn":[6.369870822],"iteration":50,"passed_time":0.03944519936,"remaining_time":0.7339900822},
{"learn":[6.325678067],"iteration":51,"passed_time":0.04008229701,"remaining_time":0.730731107},
{"learn":[6.275766122],"iteration":52,"passed_time":0.0407325495,"remaining_time":0.7278061203},
{"learn":[6.224773967],"iteration":53,"passed_time":0.04135386556,"remaining_time":0.7244584597},
{"learn":[6.182249254],"iteration":54,"passed_time":0.04197292616,"remaining_time":0.7211711859},
{"learn":[6.139904173],"iteration":55,"passed_time":0.04262811255,"remaining_time":0.7185881829},
{"learn":[6.100525536],"iteration":56,"passed_time":0.04325685419,"remaining_time":0.7156353246},
{"learn":[6.062568564],"iteration":57,"passed_time":0.04392553557,"remaining_time":0.7134112847},
{"learn":[6.030559288],"iteration":58,"passed_time":0.04463956135,"remaining_time":0.7119631735},
{"learn":[5.997931376],"iteration":59,"passed_time":0.0454081596,"remaining_time":0.7113945004},
{"learn":[5.964103835],"iteration":60,"passed_time":0.04608561717,"remaining_time":0.7094163037},
{"learn":[5.933729724],"iteration":61,"passed_time":0.04670378626,"remaining_time":0.7065830889},
{"learn":[5.901932711],"iteration":62,"passed_time":0.04736125201,"remaining_time":0.7044046529},
{"learn":[5.873727795],"iteration":63,"passed_time":0.04815558078,"remaining_time":0.704275369},
{"learn":[5.846485734],"iteration":64,"passed_time":0.04910705676,"remaining_time":0.7063861241},
{"learn":[5.820630862],"iteration":65,"passed_time":0.05000626131,"remaining_time":0.7076643646},
{"learn":[5.793646238],"iteration":66,"passed_time":0.05067360764,"remaining_time":0.7056488945},
{"learn":[5.765388646],"iteration":67,"passed_time":0.05131649513,"remaining_time":0.703337845},
{"learn":[5.747073912],"iteration":68,"passed_time":0.05198674722,"remaining_time":0.7014443719},
{"learn":[5.722315217],"iteration":69,"passed_time":0.05262040442,"remaining_time":0.6990996588},
{"learn":[5.699970599],"iteration":70,"passed_time":0.05334695531,"remaining_time":0.6980186125},
{"learn":[5.682732647],"iteration":71,"passed_time":0.05406142296,"remaining_time":0.6967916737},
{"learn":[5.663525791],"iteration":72,"passed_time":0.05475372836,"remaining_time":0.6952973451},
{"learn":[5.642381613],"iteration":73,"passed_time":0.05543875436,"remaining_time":0.6937336018},
{"learn":[5.621404779],"iteration":74,"passed_time":0.05613673899,"remaining_time":0.6923531143},
{"learn":[5.602460129],"iteration":75,"passed_time":0.05678086371,"remaining_time":0.6903357641},
{"learn":[5.587337574],"iteration":76,"passed_time":0.05739265991,"remaining_time":0.6879665597},
{"learn":[5.572393026],"iteration":77,"passed_time":0.058000277,"remaining_time":0.6855930179},
{"learn":[5.558425806],"iteration":78,"passed_time":0.05865923676,"remaining_time":0.6838627476},
{"learn":[5.541518902],"iteration":79,"passed_time":0.05939919149,"remaining_time":0.6830907022},
{"learn":[5.526157283],"iteration":80,"passed_time":0.06014464761,"remaining_time":0.682381866},
{"learn":[5.511746977],"iteration":81,"passed_time":0.06083967368,"remaining_time":0.6811075663},
{"learn":[5.504975022],"iteration":82,"passed_time":0.06122923935,"remaining_time":0.6764724396},
{"learn":[5.493980522],"iteration":83,"passed_time":0.06194394489,"remaining_time":0.6754839704},
{"learn":[5.480745463],"iteration":84,"passed_time":0.0625989523,"remaining_time":0.6738593101},
{"learn":[5.464052013],"iteration":85,"passed_time":0.0633735616,"remaining_time":0.6735283175},
{"learn":[5.449143727],"iteration":86,"passed_time":0.06443791864,"remaining_time":0.6762278128},
{"learn":[5.438255432],"iteration":87,"passed_time":0.06528579386,"remaining_time":0.6765982273},
{"learn":[5.425927931],"iteration":88,"passed_time":0.06596271563,"remaining_time":0.6751913926},
{"learn":[5.412331217],"iteration":89,"passed_time":0.06658279503,"remaining_time":0.6732260386},
{"learn":[5.400691499],"iteration":90,"passed_time":0.0672336917,"remaining_time":0.6715980852},
{"learn":[5.391618744],"iteration":91,"passed_time":0.06785801078,"remaining_time":0.669729063},
{"learn":[5.380766572],"iteration":92,"passed_time":0.06850310038,"remaining_time":0.6680893768},
{"learn":[5.372207183],"iteration":93,"passed_time":0.06916511652,"remaining_time":0.6666339954},
{"learn":[5.362918837],"iteration":94,"passed_time":0.06980143104,"remaining_time":0.6649504746},
{"learn":[5.348292324],"iteration":95,"passed_time":0.07048143699,"remaining_time":0.6637001983},
{"learn":[5.339772295],"iteration":96,"passed_time":0.07116749901,"remaining_time":0.6625180578},
{"learn":[5.331515983],"iteration":97,"passed_time":0.07185561084,"remaining_time":0.661364908},
{"learn":[5.323861644],"iteration":98,"passed_time":0.07258448668,"remaining_time":0.6605921464},
{"learn":[5.313277281],"iteration":99,"passed_time":0.07339211647,"remaining_time":0.6605290482},
{"learn":[5.30685627],"iteration":100,"passed_time":0.07413811727,"remaining_time":0.6599026478},
{"learn":[5.29652059],"iteration":101,"passed_time":0.07477723639,"remaining_time":0.6583329243},
{"learn":[5.288350766],"iteration":102,"passed_time":0.0754073153,"remaining_time":0.656702542},
{"learn":[5.27993346],"iteration":103,"passed_time":0.07604223752,"remaining_time":0.6551331233},
{"learn":[5.271789139],"iteration":104,"passed_time":0.07671642751,"remaining_time":0.6539162154},
{"learn":[5.262684686],"iteration":105,"passed_time":0.07735193388,"remaining_time":0.6523832914},
{"learn":[5.251619772],"iteration":106,"passed_time":0.07808017276,"remaining_time":0.651641068},
{"learn":[5.241012171],"iteration":107,"passed_time":0.07903788489,"remaining_time":0.6527943826},
{"learn":[5.232684032],"iteration":108,"passed_time":0.08020128951,"remaining_time":0.6555903574},
{"learn":[5.224267141],"iteration":109,"passed_time":0.08091714223,"remaining_time":0.6546932417},
{"learn":[5.216324968],"iteration":110,"passed_time":0.08175142241,"remaining_time":0.6547478786},
{"learn":[5.211102527],"iteration":111,"passed_time":0.08260100229,"remaining_time":0.6549079467},
{"learn":[5.206364257],"iteration":112,"passed_time":0.08347401888,"remaining_time":0.6552341128},
{"learn":[5.196937641],"iteration":113,"passed_time":0.08423672557,"remaining_time":0.6546819198},
{"learn":[5.190746047],"iteration":114,"passed_time":0.08492407039,"remaining_time":0.6535461069},
{"learn":[5.181885213],"iteration":115,"passed_time":0.08553747955,"remaining_time":0.6518545855},
{"learn":[5.178293568],"iteration":116,"passed_time":0.08602170971,"remaining_time":0.6492065784},
{"learn":[5.170991438],"iteration":117,"passed_time":0.08669004093,"remaining_time":0.6479713229},
{"learn":[5.166257212],"iteration":118,"passed_time":0.08735436423,"remaining_time":0.6467159234},
{"learn":[5.161421246],"iteration":119,"passed_time":0.08801789439,"remaining_time":0.6454645589},
{"learn":[5.158223542],"iteration":120,"passed_time":0.08874649954,"remaining_time":0.6446956455},
{"learn":[5.15470988],"iteration":121,"passed_time":0.08932868068,"remaining_time":0.64287362},
{"learn":[5.146388143],"iteration":122,"passed_time":0.09008449315,"remaining_time":0.6423097601},
{"learn":[5.139529364],"iteration":123,"passed_time":0.09079091882,"remaining_time":0.6413939104},
{"learn":[5.134276023],"iteration":124,"passed_time":0.0914510052,"remaining_time":0.6401570364},
{"learn":[5.128536065],"iteration":125,"passed_time":0.09207675883,"remaining_time":0.6386911684},
{"learn":[5.123300353],"iteration":126,"passed_time":0.09257451511,"remaining_time":0.6363586747},
{"learn":[5.116200518],"iteration":127,"passed_time":0.09338255731,"remaining_time":0.6361686717},
{"learn":[5.108728704],"iteration":128,"passed_time":0.09439230242,"remaining_time":0.6373309722},
{"learn":[5.104075866],"iteration":129,"passed_time":0.0951564003,"remaining_time":0.6368159097},
{"learn":[5.100317606],"iteration":130,"passed_time":0.09583504897,"remaining_time":0.6357302103},
{"learn":[5.095814182],"iteration":131,"passed_time":0.0965060514,"remaining_time":0.6346003986},
{"learn":[5.092146915],"iteration":132,"passed_time":0.09711662593,"remaining_time":0.6330835691},
{"learn":[5.085258329],"iteration":133,"passed_time":0.09784265659,"remaining_time":0.6323264224},
{"learn":[5.079219421],"iteration":134,"passed_time":0.09863163406,"remaining_time":0.6319730627},
{"learn":[5.076476829],"iteration":135,"passed_time":0.09932102536,"remaining_time":0.6309806317},
{"learn":[5.072133867],"iteration":136,"passed_time":0.09999845403,"remaining_time":0.6299172688},
{"learn":[5.067031564],"iteration":137,"passed_time":0.1006592958,"remaining_time":0.6287558909},
{"learn":[5.061358312],"iteration":138,"passed_time":0.1013054169,"remaining_time":0.6275105322},
{"learn":[5.056759124],"iteration":139,"passed_time":0.1019342736,"remaining_time":0.6261676808},
{"learn":[5.050254],"iteration":140,"passed_time":0.1025990771,"remaining_time":0.6250539522},
{"learn":[5.048376474],"iteration":141,"passed_time":0.1030100814,"remaining_time":0.622413027},
{"learn":[5.042603751],"iteration":142,"passed_time":0.1036255454,"remaining_time":0.6210286181},
{"learn":[5.037477349],"iteration":143,"passed_time":0.104256209,"remaining_time":0.6197452424},
{"learn":[5.03230489],"iteration":144,"passed_time":0.1048725033,"remaining_time":0.6183861404},
{"learn":[5.025976187],"iteration":145,"passed_time":0.1055990559,"remaining_time":0.6176821489},
{"learn":[5.01952451],"iteration":146,"passed_time":0.1062566067,"remaining_time":0.6165774525},
{"learn":[5.017569424],"iteration":147,"passed_time":0.1069443039,"remaining_time":0.6156523441},
{"learn":[5.008962367],"iteration":148,"passed_time":0.1076086878,"remaining_time":0.6145972705},
{"learn":[5.003880266],"iteration":149,"passed_time":0.108289005,"remaining_time":0.6136376949},
{"learn":[4.996387564],"iteration":150,"passed_time":0.109215533,"remaining_time":0.6140661425},
{"learn":[4.993361683],"iteration":151,"passed_time":0.1103300088,"remaining_time":0.6155253124},
{"learn":[4.99005752],"iteration":152,"passed_time":0.1110238849,"remaining_time":0.6146224218},
{"learn":[4.986908764],"iteration":153,"passed_time":0.1117236754,"remaining_time":0.6137547362},
{"learn":[4.985207175],"iteration":154,"passed_time":0.1123470735,"remaining_time":0.6124727555},
{"learn":[4.979003494],"iteration":155,"passed_time":0.1129885142,"remaining_time":0.6112968334},
{"learn":[4.973142217],"iteration":156,"passed_time":0.1136123726,"remaining_time":0.6100333125},
{"learn":[4.967056696],"iteration":157,"passed_time":0.114246988,"remaining_time":0.6088352144},
{"learn":[4.961460696],"iteration":158,"passed_time":0.1148900594,"remaining_time":0.6076889307},
{"learn":[4.954240363],"iteration":159,"passed_time":0.1155752855,"remaining_time":0.606770249},
{"learn":[4.952320707],"iteration":160,"passed_time":0.1160837333,"remaining_time":0.6049332437},
{"learn":[4.948337777],"iteration":161,"passed_time":0.1168910524,"remaining_time":0.6046586537},
{"learn":[4.943228639],"iteration":162,"passed_time":0.1175515273,"remaining_time":0.6036234867},
{"learn":[4.938545759],"iteration":163,"passed_time":0.118249966,"remaining_time":0.6027864121},
{"learn":[4.935330572],"iteration":164,"passed_time":0.1189298136,"remaining_time":0.6018569353},
{"learn":[4.932051543],"iteration":165,"passed_time":0.1195941035,"remaining_time":0.6008523032},
{"learn":[4.928964153],"iteration":166,"passed_time":0.1201814798,"remaining_time":0.5994680997},
{"learn":[4.922860227],"iteration":167,"passed_time":0.1208339105,"remaining_time":0.5984155566},
{"learn":[4.917668772],"iteration":168,"passed_time":0.1214924506,"remaining_time":0.5973977896},
{"learn":[4.910365386],"iteration":169,"passed_time":0.1221508523,"remaining_time":0.5963835731},
{"learn":[4.906457206],"iteration":170,"passed_time":0.1228094019,"remaining_time":0.5953742349},
{"learn":[4.901996508],"iteration":171,"passed_time":0.1235008175,"remaining_time":0.594527191},
{"learn":[4.896816173],"iteration":172,"passed_time":0.1244187105,"remaining_time":0.594764587},
{"learn":[4.891123132],"iteration":173,"passed_time":0.1253293352,"remaining_time":0.5949542003},
{"learn":[4.887630202],"iteration":174,"passed_time":0.1261606774,"remaining_time":0.594757479},
{"learn":[4.885259712],"iteration":175,"passed_time":0.1269428751,"remaining_time":0.5943234606},
{"learn":[4.880659728],"iteration":176,"passed_time":0.127662594,"remaining_time":0.5935949992},
{"learn":[4.877299723],"iteration":177,"passed_time":0.128273875,"remaining_time":0.592365872},
{"learn":[4.874038772],"iteration":178,"passed_time":0.1288925921,"remaining_time":0.5911777547},
{"learn":[4.86943698],"iteration":179,"passed_time":0.1295156328,"remaining_time":0.5900156606},
{"learn":[4.861268711],"iteration":180,"passed_time":0.1302609933,"remaining_time":0.5894130029},
{"learn":[4.858673056],"iteration":181,"passed_time":0.131198737,"remaining_time":0.5896734442},
{"learn":[4.854036207],"iteration":182,"passed_time":0.1319575497,"remaining_time":0.5891219568},
{"learn":[4.85130244],"iteration":183,"passed_time":0.1326593233,"remaining_time":0.5883152597},
{"learn":[4.847510084],"iteration":184,"passed_time":0.1333338662,"remaining_time":0.5873897348},
{"learn":[4.845691673],"iteration":185,"passed_time":0.1339473926,"remaining_time":0.5861998795},
{"learn":[4.842058646],"iteration":186,"passed_time":0.134632044,"remaining_time":0.5853254105},
{"learn":[4.838623675],"iteration":187,"passed_time":0.1352978074,"remaining_time":0.5843713808},
{"learn":[4.834602161],"iteration":188,"passed_time":0.1359609535,"remaining_time":0.5834091708},
{"learn":[4.830858976],"iteration":189,"passed_time":0.1366104851,"remaining_time":0.582392068},
{"learn":[4.827590511],"iteration":190,"passed_time":0.1372936141,"remaining_time":0.5815211195},
{"learn":[4.822246226],"iteration":191,"passed_time":0.1379308891,"remaining_time":0.5804591581},
{"learn":[4.816686395],"iteration":192,"passed_time":0.1385971066,"remaining_time":0.5795226165},
{"learn":[4.814797121],"iteration":193,"passed_time":0.1395374308,"remaining_time":0.5797276765},
{"learn":[4.811639392],"iteration":194,"passed_time":0.1404623081,"remaining_time":0.5798572206},
{"learn":[4.804813432],"iteration":195,"passed_time":0.1411520457,"remaining_time":0.5790114526},
{"learn":[4.80251613],"iteration":196,"passed_time":0.1418082169,"remaining_time":0.5780304477},
{"learn":[4.800087884],"iteration":197,"passed_time":0.1424467886,"remaining_time":0.5769814366},
{"learn":[4.794773135],"iteration":198,"passed_time":0.1430632658,"remaining_time":0.5758476176},
{"learn":[4.791664833],"iteration":199,"passed_time":0.1437513265,"remaining_time":0.575005306},
{"learn":[4.785989873],"iteration":200,"passed_time":0.1446773876,"remaining_time":0.5751106106},
{"learn":[4.782387142],"iteration":201,"passed_time":0.1455626509,"remaining_time":0.5750445317},
{"learn":[4.778623704],"iteration":202,"passed_time":0.1462695818,"remaining_time":0.57427023},
{"learn":[4.775772178],"iteration":203,"passed_time":0.1469109769,"remaining_time":0.5732408708},
{"learn":[4.77023101],"iteration":204,"passed_time":0.1475432702,"remaining_time":0.572179999},
{"learn":[4.764496689],"iteration":205,"passed_time":0.1481908943,"remaining_time":0.5711823789},
{"learn":[4.763138716],"iteration":206,"passed_time":0.1488246676,"remaining_time":0.5701350794},
{"learn":[4.758053283],"iteration":207,"passed_time":0.1495179424,"remaining_time":0.569318319},
{"learn":[4.755063788],"iteration":208,"passed_time":0.150137322,"remaining_time":0.5682230703},
{"learn":[4.752465267],"iteration":209,"passed_time":0.1507790717,"remaining_time":0.567216508},
{"learn":[4.748067377],"iteration":210,"passed_time":0.1514742173,"remaining_time":0.5664130686},
{"learn":[4.744163298],"iteration":211,"passed_time":0.1521080607,"remaining_time":0.5653827917},
{"learn":[4.736670896],"iteration":212,"passed_time":0.1528088044,"remaining_time":0.5646034228},
{"learn":[4.73349255],"iteration":213,"passed_time":0.1534570665,"remaining_time":0.5636320294},
{"learn":[4.731864595],"iteration":214,"passed_time":0.1543552306,"remaining_time":0.5635760745},
{"learn":[4.728398311],"iteration":215,"passed_time":0.1554931242,"remaining_time":0.5643824509},
{"learn":[4.723865975],"iteration":216,"passed_time":0.1562307696,"remaining_time":0.563726694},
{"learn":[4.723483365],"iteration":217,"passed_time":0.1568533307,"remaining_time":0.5626573605},
{"learn":[4.72095416],"iteration":218,"passed_time":0.1574916522,"remaining_time":0.5616483122},
{"learn":[4.716173382],"iteration":219,"passed_time":0.1581484816,"remaining_time":0.5607082528},
{"learn":[4.710563974],"iteration":220,"passed_time":0.1588002631,"remaining_time":0.5597529635},
{"learn":[4.707160263],"iteration":221,"passed_time":0.1594186834,"remaining_time":0.558683494},
{"learn":[4.70408351],"iteration":222,"passed_time":0.1600366596,"remaining_time":0.5576165224},
{"learn":[4.702501831],"iteration":223,"passed_time":0.1606532152,"remaining_time":0.5565486383},
{"learn":[4.700269738],"iteration":224,"passed_time":0.1612768673,"remaining_time":0.5555092096},
{"learn":[4.695346302],"iteration":225,"passed_time":0.1620200035,"remaining_time":0.5548826667},
{"learn":[4.689769299],"iteration":226,"passed_time":0.1627615573,"remaining_time":0.5542497082},
{"learn":[4.687919514],"iteration":227,"passed_time":0.1634640173,"remaining_time":0.5534834268},
{"learn":[4.682982074],"iteration":228,"passed_time":0.1641830659,"remaining_time":0.5527735536},
{"learn":[4.679578702],"iteration":229,"passed_time":0.1648339898,"remaining_time":0.5518355309},
{"learn":[4.675751423],"iteration":230,"passed_time":0.1654791066,"remaining_time":0.5508806622},
{"learn":[4.672710726],"iteration":231,"passed_time":0.1661120824,"remaining_time":0.5498882727},
{"learn":[4.6690533],"iteration":232,"passed_time":0.1667447964,"remaining_time":0.5488981065},
{"learn":[4.667595702],"iteration":233,"passed_time":0.1674545169,"remaining_time":0.5481630766},
{"learn":[4.664241291],"iteration":234,"passed_time":0.1680946642,"remaining_time":0.5472017793},
{"learn":[4.662246999],"iteration":235,"passed_time":0.1687193952,"remaining_time":0.5461932963},
{"learn":[4.658668443],"iteration":236,"passed_time":0.1695627856,"remaining_time":0.5458920059},
{"learn":[4.658017572],"iteration":237,"passed_time":0.1705448165,"remaining_time":0.5460300427},
{"learn":[4.657656705],"iteration":238,"passed_time":0.1713407716,"remaining_time":0.5455662224},
{"learn":[4.653242871],"iteration":239,"passed_time":0.1720269436,"remaining_time":0.5447519882},
{"learn":[4.6507302],"iteration":240,"passed_time":0.1727803161,"remaining_time":0.5441504561},
{"learn":[4.647671336],"iteration":241,"passed_time":0.1734409405,"remaining_time":0.5432571608},
{"learn":[4.645506007],"iteration":242,"passed_time":0.1740970295,"remaining_time":0.5423516516},
{"learn":[4.641297906],"iteration":243,"passed_time":0.1747381946,"remaining_time":0.5414019471},
{"learn":[4.63798107],"iteration":244,"passed_time":0.1753509595,"remaining_time":0.5403672427},
{"learn":[4.635062318],"iteration":245,"passed_time":0.1759791926,"remaining_time":0.539383379},
{"learn":[4.631606017],"iteration":246,"passed_time":0.1765920849,"remaining_time":0.5383556272},
{"learn":[4.630215494],"iteration":247,"passed_time":0.1771695183,"remaining_time":0.5372237007},
{"learn":[4.62729814],"iteration":248,"passed_time":0.1778014131,"remaining_time":0.5362604868},
{"learn":[4.624691756],"iteration":249,"passed_time":0.1784275274,"remaining_time":0.5352825822},
{"learn":[4.621840053],"iteration":250,"passed_time":0.1790724102,"remaining_time":0.5343634871},
{"learn":[4.619602091],"iteration":251,"passed_time":0.1797208869,"remaining_time":0.5334572358},
{"learn":[4.613584029],"iteration":252,"passed_time":0.180406392,"remaining_time":0.5326623511},
{"learn":[4.6119388],"iteration":253,"passed_time":0.1810386186,"remaining_time":0.5317118483},
{"learn":[4.60870702],"iteration":254,"passed_time":0.1816751015,"remaining_time":0.5307762769},
{"learn":[4.604771557],"iteration":255,"passed_time":0.1823286427,"remaining_time":0.5298926178},
{"learn":[4.604231277],"iteration":256,"passed_time":0.1830042867,"remaining_time":0.5290746498},
{"learn":[4.600750354],"iteration":257,"passed_time":0.1836401821,"remaining_time":0.5281434695},
{"learn":[4.596488253],"iteration":258,"passed_time":0.1843962097,"remaining_time":0.5275582678},
{"learn":[4.59470784],"iteration":259,"passed_time":0.1852774522,"remaining_time":0.5273281332},
{"learn":[4.588818005],"iteration":260,"passed_time":0.1862845973,"remaining_time":0.5274494918},
{"learn":[4.585054174],"iteration":261,"passed_time":0.1871629357,"remaining_time":0.5271994143},
{"learn":[4.581471435],"iteration":262,"passed_time":0.1879190355,"remaining_time":0.5266020121},
{"learn":[4.577555199],"iteration":263,"passed_time":0.1887302658,"remaining_time":0.5261571047},
{"learn":[4.57457145],"iteration":264,"passed_time":0.189486583,"remaining_time":0.5255571263},
{"learn":[4.573029224],"iteration":265,"passed_time":0.1903907297,"remaining_time":0.5253638933},
{"learn":[4.571326203],"iteration":266,"passed_time":0.1911513266,"remaining_time":0.5247712449},
{"learn":[4.571019224],"iteration":267,"passed_time":0.1917690171,"remaining_time":0.5237870169},
{"learn":[4.565766631],"iteration":268,"passed_time":0.1924317803,"remaining_time":0.5229279977},
{"learn":[4.563383471],"iteration":269,"passed_time":0.1930816242,"remaining_time":0.5220355026},
{"learn":[4.558165805],"iteration":270,"passed_time":0.1937219067,"remaining_time":0.5211190773},
{"learn":[4.55629209],"iteration":271,"passed_time":0.1943508701,"remaining_time":0.5201743876},
{"learn":[4.549383848],"iteration":272,"passed_time":0.1949878427,"remaining_time":0.5192533393},
{"learn":[4.546227503],"iteration":273,"passed_time":0.1956080921,"remaining_time":0.5182900544},
{"learn":[4.540620977],"iteration":274,"passed_time":0.1962568067,"remaining_time":0.5174043086},
{"learn":[4.532898237],"iteration":275,"passed_time":0.1969340942,"remaining_time":0.5165952326},
{"learn":[4.529757367],"iteration":276,"passed_time":0.1975862942,"remaining_time":0.5157216272},
{"learn":[4.52579294],"iteration":277,"passed_time":0.1982795617,"remaining_time":0.5149562719},
{"learn":[4.521572155],"iteration":278,"passed_time":0.1990096259,"remaining_time":0.5142865243},
{"learn":[4.518818099],"iteration":279,"passed_time":0.200145652,"remaining_time":0.514660248},
{"learn":[4.514012334],"iteration":280,"passed_time":0.2013422155,"remaining_time":0.5151781244},
{"learn":[4.508331416],"iteration":281,"passed_time":0.2020803644,"remaining_time":0.5145166726},
{"learn":[4.506038537],"iteration":282,"passed_time":0.2027453464,"remaining_time":0.5136693051},
{"learn":[4.505805643],"iteration":283,"passed_time":0.2033478789,"remaining_time":0.5126657793},
{"learn":[4.501550352],"iteration":284,"passed_time":0.2039861716,"remaining_time":0.5117547813},
{"learn":[4.494692643],"iteration":285,"passed_time":0.2046170019,"remaining_time":0.5108270608},
{"learn":[4.489330245],"iteration":286,"passed_time":0.2053469849,"remaining_time":0.5101477361},
{"learn":[4.484826955],"iteration":287,"passed_time":0.2060027983,"remaining_time":0.5092846957},
{"learn":[4.478285428],"iteration":288,"passed_time":0.2066788674,"remaining_time":0.508472923},
{"learn":[4.475311671],"iteration":289,"passed_time":0.2074242396,"remaining_time":0.5078317591},
{"learn":[4.471581298],"iteration":290,"passed_time":0.2081338317,"remaining_time":0.5071027034},
{"learn":[4.469164956],"iteration":291,"passed_time":0.208786751,"remaining_time":0.5062363688},
{"learn":[4.462068024],"iteration":292,"passed_time":0.2094977276,"remaining_time":0.5055115816},
{"learn":[4.458540976],"iteration":293,"passed_time":0.2102140378,"remaining_time":0.5047996961},
{"learn":[4.455757458],"iteration":294,"passed_time":0.2108849201,"remaining_time":0.5039792159},
{"learn":[4.453027414],"iteration":295,"passed_time":0.2115864319,"remaining_time":0.5032325948},
{"learn":[4.450659338],"iteration":296,"passed_time":0.2122363587,"remaining_time":0.5023641757},
{"learn":[4.444696901],"iteration":297,"passed_time":0.2128803022,"remaining_time":0.5014831281},
{"learn":[4.442052813],"iteration":298,"passed_time":0.2135228718,"remaining_time":0.5006004452},
{"learn":[4.440036756],"iteration":299,"passed_time":0.214131531,"remaining_time":0.4996402391},
{"learn":[4.435017051],"iteration":300,"passed_time":0.2150104114,"remaining_time":0.4993098922},
{"learn":[4.429962125],"iteration":301,"passed_time":0.2161298706,"remaining_time":0.4995319525},
{"learn":[4.427666256],"iteration":302,"passed_time":0.2169632364,"remaining_time":0.4990870489},
{"learn":[4.425030004],"iteration":303,"passed_time":0.2176888219,"remaining_time":0.4983928291},
{"learn":[4.422588771],"iteration":304,"passed_time":0.2183662317,"remaining_time":0.4975886263},
{"learn":[4.418936667],"iteration":305,"passed_time":0.2190566201,"remaining_time":0.4968146874},
{"learn":[4.416887976],"iteration":306,"passed_time":0.2197023155,"remaining_time":0.495940406},
{"learn":[4.413773354],"iteration":307,"passed_time":0.2203302079,"remaining_time":0.4950276099},
{"learn":[4.411129391],"iteration":308,"passed_time":0.2209665024,"remaining_time":0.4941354471},
{"learn":[4.40850819],"iteration":309,"passed_time":0.2216056182,"remaining_time":0.4932512147},
{"learn":[4.404880292],"iteration":310,"passed_time":0.2222962667,"remaining_time":0.492482726},
{"learn":[4.404593827],"iteration":311,"passed_time":0.2228909841,"remaining_time":0.4915031957},
{"learn":[4.402139942],"iteration":312,"passed_time":0.2235027219,"remaining_time":0.4905634823},
{"learn":[4.400284725],"iteration":313,"passed_time":0.2241943637,"remaining_time":0.4898004251},
{"learn":[4.395805521],"iteration":314,"passed_time":0.22484686,"remaining_time":0.4889526955},
{"learn":[4.392838833],"iteration":315,"passed_time":0.2255150117,"remaining_time":0.4881400886},
{"learn":[4.389213061],"iteration":316,"passed_time":0.2261669688,"remaining_time":0.4872935006},
{"learn":[4.3861981],"iteration":317,"passed_time":0.2267925296,"remaining_time":0.4863915257},
{"learn":[4.385054234],"iteration":318,"passed_time":0.2274005658,"remaining_time":0.4854538723},
{"learn":[4.379364607],"iteration":319,"passed_time":0.228020718,"remaining_time":0.4845440257},
{"learn":[4.378387619],"iteration":320,"passed_time":0.2286196117,"remaining_time":0.4835910166},
{"learn":[4.375816727],"iteration":321,"passed_time":0.2292483005,"remaining_time":0.4827029433},
{"learn":[4.374600202],"iteration":322,"passed_time":0.2300810533,"remaining_time":0.4822441892},
{"learn":[4.37098897],"iteration":323,"passed_time":0.2310025724,"remaining_time":0.4819683301},
{"learn":[4.367418484],"iteration":324,"passed_time":0.2317847913,"remaining_time":0.4813991819},
{"learn":[4.363584638],"iteration":325,"passed_time":0.2324686545,"remaining_time":0.4806253777},
{"learn":[4.360770706],"iteration":326,"passed_time":0.2331039675,"remaining_time":0.4797522021},
{"learn":[4.358675808],"iteration":327,"passed_time":0.2337507701,"remaining_time":0.4789040167},
{"learn":[4.354228195],"iteration":328,"passed_time":0.2343879872,"remaining_time":0.4780375058},
{"learn":[4.353773425],"iteration":329,"passed_time":0.2350382036,"remaining_time":0.4771987769},
{"learn":[4.351648009],"iteration":330,"passed_time":0.2357282574,"remaining_time":0.4764417045},
{"learn":[4.348209927],"iteration":331,"passed_time":0.2364374499,"remaining_time":0.4757235437},
{"learn":[4.345852733],"iteration":332,"passed_time":0.2370972128,"remaining_time":0.4749064292},
{"learn":[4.34237339],"iteration":333,"passed_time":0.2377228875,"remaining_time":0.4740222846},
{"learn":[4.340814362],"iteration":334,"passed_time":0.2383657422,"remaining_time":0.4731737867},
{"learn":[4.339707068],"iteration":335,"passed_time":0.2389973768,"remaining_time":0.4723043399},
{"learn":[4.335430786],"iteration":336,"passed_time":0.239634819,"remaining_time":0.47144773},
{"learn":[4.33521887],"iteration":337,"passed_time":0.240222645,"remaining_time":0.4704952395},
{"learn":[4.328507238],"iteration":338,"passed_time":0.2408541818,"remaining_time":0.4696301302},
{"learn":[4.326140732],"iteration":339,"passed_time":0.2414707985,"remaining_time":0.4687374323},
{"learn":[4.323785636],"iteration":340,"passed_time":0.242099414,"remaining_time":0.4678695419},
{"learn":[4.320632534],"iteration":341,"passed_time":0.2427405045,"remaining_time":0.4670270526},
{"learn":[4.31973724],"iteration":342,"passed_time":0.2433527732,"remaining_time":0.4661305305},
{"learn":[4.318000924],"iteration":343,"passed_time":0.2441965237,"remaining_time":0.4656770918},
{"learn":[4.312713628],"iteration":344,"passed_time":0.2458865432,"remaining_time":0.4668280749},
{"learn":[4.308220789],"iteration":345,"passed_time":0.2471491283,"remaining_time":0.4671547107},
{"learn":[4.305890947],"iteration":346,"passed_time":0.2480288446,"remaining_time":0.4667516873},
{"learn":[4.305137856],"iteration":347,"passed_time":0.2488499205,"remaining_time":0.4662360579},
{"learn":[4.304787172],"iteration":348,"passed_time":0.2496461429,"remaining_time":0.4656723181},
{"learn":[4.30350134],"iteration":349,"passed_time":0.2503336216,"remaining_time":0.4649052973},
{"learn":[4.30293809],"iteration":350,"passed_time":0.2509750807,"remaining_time":0.4640536392},
{"learn":[4.299548459],"iteration":351,"passed_time":0.2516058538,"remaining_time":0.4631835036},
{"learn":[4.294768408],"iteration":352,"passed_time":0.2522381037,"remaining_time":0.4623174309},
{"learn":[4.294581479],"iteration":353,"passed_time":0.2529038832,"remaining_time":0.461513866},
{"learn":[4.292551604],"iteration":354,"passed_time":0.2535678013,"remaining_time":0.4607076954},
{"learn":[4.288628894],"iteration":355,"passed_time":0.2542188937,"remaining_time":0.4598791222},
{"learn":[4.287802767],"iteration":356,"passed_time":0.2548731602,"remaining_time":0.4590572605},
{"learn":[4.284566905],"iteration":357,"passed_time":0.2554896241,"remaining_time":0.4581685437},
{"learn":[4.27890232],"iteration":358,"passed_time":0.2561713624,"remaining_time":0.4573978923},
{"learn":[4.276938023],"iteration":359,"passed_time":0.2568049835,"remaining_time":0.4565421929},
{"learn":[4.273425094],"iteration":360,"passed_time":0.2574969704,"remaining_time":0.4557910363},
{"learn":[4.269726505],"iteration":361,"passed_time":0.2581674615,"remaining_time":0.4550023217},
{"learn":[4.265565857],"iteration":362,"passed_time":0.2588312813,"remaining_time":0.4542025514},
{"learn":[4.262117173],"iteration":363,"passed_time":0.2595169403,"remaining_time":0.453441687},
{"learn":[4.259185148],"iteration":364,"passed_time":0.2603279667,"remaining_time":0.4528993393},
{"learn":[4.257668507],"iteration":365,"passed_time":0.261265867,"remaining_time":0.4525752998},
{"learn":[4.253432436],"iteration":366,"passed_time":0.2620349694,"remaining_time":0.4519567729},
{"learn":[4.250216667],"iteration":367,"passed_time":0.2630159032,"remaining_time":0.451701225},
{"learn":[4.24514828],"iteration":368,"passed_time":0.2638265326,"remaining_time":0.4511505206},
{"learn":[4.244015772],"iteration":369,"passed_time":0.2644991947,"remaining_time":0.4503634937},
{"learn":[4.240329192],"iteration":370,"passed_time":0.2652965332,"remaining_time":0.4497884619},
{"learn":[4.236718014],"iteration":371,"passed_time":0.2660652003,"remaining_time":0.4491638328},
{"learn":[4.233495944],"iteration":372,"passed_time":0.2668728802,"remaining_time":0.4486040103},
{"learn":[4.230357491],"iteration":373,"passed_time":0.2676761902,"remaining_time":0.4480355483},
{"learn":[4.227381215],"iteration":374,"passed_time":0.2684789133,"remaining_time":0.4474648556},
{"learn":[4.226169067],"iteration":375,"passed_time":0.2692123963,"remaining_time":0.4467780193},
{"learn":[4.225963861],"iteration":376,"passed_time":0.2699801802,"remaining_time":0.4461476188},
{"learn":[4.224346548],"iteration":377,"passed_time":0.2708884522,"remaining_time":0.4457476648},
{"learn":[4.222595381],"iteration":378,"passed_time":0.2716942623,"remaining_time":0.4451771422},
{"learn":[4.219700938],"iteration":379,"passed_time":0.272610051,"remaining_time":0.4447848201},
{"learn":[4.216356207],"iteration":380,"passed_time":0.2733685764,"remaining_time":0.4441342488},
{"learn":[4.214326494],"iteration":381,"passed_time":0.2740750832,"remaining_time":0.4433989566},
{"learn":[4.212901398],"iteration":382,"passed_time":0.2747795147,"remaining_time":0.4426604714},
{"learn":[4.211331091],"iteration":383,"passed_time":0.2757769442,"remaining_time":0.4423921813},
{"learn":[4.208624791],"iteration":384,"passed_time":0.2769452282,"remaining_time":0.4423930269},
{"learn":[4.204659106],"iteration":385,"passed_time":0.2778703262,"remaining_time":0.4420009852},
{"learn":[4.202968852],"iteration":386,"passed_time":0.278706505,"remaining_time":0.4414653425},
{"learn":[4.197261935],"iteration":387,"passed_time":0.2795183817,"remaining_time":0.4408898186},
{"learn":[4.196934403],"iteration":388,"passed_time":0.2802548037,"remaining_time":0.4401945632},
{"learn":[4.192479929],"iteration":389,"passed_time":0.2810872475,"remaining_time":0.4396492846},
{"learn":[4.190243116],"iteration":390,"passed_time":0.2818981755,"remaining_time":0.4390690252},
{"learn":[4.185852431],"iteration":391,"passed_time":0.2826166077,"remaining_time":0.4383441262},
{"learn":[4.180967944],"iteration":392,"passed_time":0.283309714,"remaining_time":0.4375801435},
{"learn":[4.178283162],"iteration":393,"passed_time":0.2839870465,"remaining_time":0.4367922594},
{"learn":[4.176341157],"iteration":394,"passed_time":0.2846371289,"remaining_time":0.4359631975},
{"learn":[4.176041504],"iteration":395,"passed_time":0.2853246505,"remaining_time":0.4351921437},
{"learn":[4.175564513],"iteration":396,"passed_time":0.2859759012,"remaining_time":0.4343664192},
{"learn":[4.170830274],"iteration":397,"passed_time":0.2866802415,"remaining_time":0.4336218728},
{"learn":[4.167804808],"iteration":398,"passed_time":0.2873077865,"remaining_time":0.4327618539},
{"learn":[4.165860548],"iteration":399,"passed_time":0.2879702006,"remaining_time":0.4319553009},
{"learn":[4.160950571],"iteration":400,"passed_time":0.2887065948,"remaining_time":0.4312599758},
{"learn":[4.158544115],"iteration":401,"passed_time":0.2893694892,"remaining_time":0.4304551107},
{"learn":[4.154448767],"iteration":402,"passed_time":0.2904330631,"remaining_time":0.4302445128},
{"learn":[4.15197457],"iteration":403,"passed_time":0.291711134,"remaining_time":0.4303461284},
{"learn":[4.149562679],"iteration":404,"passed_time":0.2924791453,"remaining_time":0.4296915839},
{"learn":[4.149327961],"iteration":405,"passed_time":0.2931343245,"remaining_time":0.4288714008},
{"learn":[4.147444889],"iteration":406,"passed_time":0.2937665633,"remaining_time":0.4280186045},
{"learn":[4.147254809],"iteration":407,"passed_time":0.2943925375,"remaining_time":0.4271577996},
{"learn":[4.144589165],"iteration":408,"passed_time":0.2950268539,"remaining_time":0.4263101973},
{"learn":[4.141691034],"iteration":409,"passed_time":0.2956878602,"remaining_time":0.4255020427},
{"learn":[4.138893468],"iteration":410,"passed_time":0.2963349435,"remaining_time":0.4246746513},
{"learn":[4.136964597],"iteration":411,"passed_time":0.296992706,"remaining_time":0.4238633765},
{"learn":[4.133773523],"iteration":412,"passed_time":0.297599535,"remaining_time":0.4229804528},
{"learn":[4.131363444],"iteration":413,"passed_time":0.2982600299,"remaining_time":0.4221748249},
{"learn":[4.130228592],"iteration":414,"passed_time":0.2989060743,"remaining_time":0.4213495265},
{"learn":[4.12884186],"iteration":415,"passed_time":0.2995243012,"remaining_time":0.4204860383},
{"learn":[4.12413494],"iteration":416,"passed_time":0.300134968,"remaining_time":0.4196131567},
{"learn":[4.119422508],"iteration":417,"passed_time":0.3009115877,"remaining_time":0.4189725934},
{"learn":[4.117038244],"iteration":418,"passed_time":0.301631156,"remaining_time":0.4182522712},
{"learn":[4.116067631],"iteration":419,"passed_time":0.3023556387,"remaining_time":0.4175387392},
{"learn":[4.110343455],"iteration":420,"passed_time":0.3031556423,"remaining_time":0.4169290187},
{"learn":[4.105604544],"iteration":421,"passed_time":0.3040125644,"remaining_time":0.4163963559},
{"learn":[4.103390131],"iteration":422,"passed_time":0.3047879273,"remaining_time":0.415750908},
{"learn":[4.096724402],"iteration":423,"passed_time":0.3059430293,"remaining_time":0.4156207191},
{"learn":[4.093431279],"iteration":424,"passed_time":0.307544307,"remaining_time":0.4160893565},
{"learn":[4.091412744],"iteration":425,"passed_time":0.3083595908,"remaining_time":0.4154892139},
{"learn":[4.091192901],"iteration":426,"passed_time":0.3093268167,"remaining_time":0.4150919578},
{"learn":[4.088994581],"iteration":427,"passed_time":0.3106147143,"remaining_time":0.4151205995},
{"learn":[4.087845355],"iteration":428,"passed_time":0.311509264,"remaining_time":0.4146195565},
{"learn":[4.083650279],"iteration":429,"passed_time":0.312288696,"remaining_time":0.4139640854},
{"learn":[4.079840652],"iteration":430,"passed_time":0.3130552472,"remaining_time":0.413291034},
{"learn":[4.075707828],"iteration":431,"passed_time":0.3139023993,"remaining_time":0.412723525},
{"learn":[4.071345409],"iteration":432,"passed_time":0.3149764869,"remaining_time":0.4124518893},
{"learn":[4.067460475],"iteration":433,"passed_time":0.3158166158,"remaining_time":0.4118714391},
{"learn":[4.064914749],"iteration":434,"passed_time":0.3165252341,"remaining_time":0.4111189823},
{"learn":[4.063823175],"iteration":435,"passed_time":0.3172413742,"remaining_time":0.4103764566},
{"learn":[4.058898471],"iteration":436,"passed_time":0.3179757298,"remaining_time":0.4096575191},
{"learn":[4.054120355],"iteration":437,"passed_time":0.3186091457,"remaining_time":0.4088089952},
{"learn":[4.052715901],"iteration":438,"passed_time":0.3192474889,"remaining_time":0.4079677478},
{"learn":[4.052114167],"iteration":439,"passed_time":0.3198807754,"remaining_time":0.4071209869},
{"learn":[4.051377267],"iteration":440,"passed_time":0.3207325896,"remaining_time":0.4065521941},
{"learn":[4.049275336],"iteration":441,"passed_time":0.3218288283,"remaining_time":0.4062906928},
{"learn":[4.047099198],"iteration":442,"passed_time":0.3237816112,"remaining_time":0.4071023869},
{"learn":[4.044348685],"iteration":443,"passed_time":0.3247575471,"remaining_time":0.4066783698},
{"learn":[4.042822379],"iteration":444,"passed_time":0.3254669341,"remaining_time":0.4059194347},
{"learn":[4.041258611],"iteration":445,"passed_time":0.3262506236,"remaining_time":0.4052530168},
{"learn":[4.040044254],"iteration":446,"passed_time":0.3271319834,"remaining_time":0.4047069057},
{"learn":[4.036860137],"iteration":447,"passed_time":0.3280045326,"remaining_time":0.4041484419},
{"learn":[4.036372284],"iteration":448,"passed_time":0.3288782317,"remaining_time":0.4035899904},
{"learn":[4.03368231],"iteration":449,"passed_time":0.3297898208,"remaining_time":0.4030764476},
{"learn":[4.032439519],"iteration":450,"passed_time":0.3305426519,"remaining_time":0.4023678844},
{"learn":[4.032008634],"iteration":451,"passed_time":0.3311754359,"remaining_time":0.4015135816},
{"learn":[4.030034932],"iteration":452,"passed_time":0.3318729792,"remaining_time":0.4007384539},
{"learn":[4.028173412],"iteration":453,"passed_time":0.3324969409,"remaining_time":0.3998751757},
{"learn":[4.023806097],"iteration":454,"passed_time":0.3331559251,"remaining_time":0.3990548993},
{"learn":[4.020239186],"iteration":455,"passed_time":0.3338307221,"remaining_time":0.3982541947},
{"learn":[4.017384838],"iteration":456,"passed_time":0.3345620346,"remaining_time":0.397521192},
{"learn":[4.016468229],"iteration":457,"passed_time":0.335467826,"remaining_time":0.3969946762},
{"learn":[4.014530169],"iteration":458,"passed_time":0.3364525948,"remaining_time":0.3965595943},
{"learn":[4.012884822],"iteration":459,"passed_time":0.3382320064,"remaining_time":0.397054964},
{"learn":[4.008924707],"iteration":460,"passed_time":0.3389931852,"remaining_time":0.3963499497},
{"learn":[4.008286778],"iteration":461,"passed_time":0.3396843289,"remaining_time":0.3955631363},
{"learn":[4.006444202],"iteration":462,"passed_time":0.340461331,"remaining_time":0.3948763169},
{"learn":[4.003284363],"iteration":463,"passed_time":0.3412135574,"remaining_time":0.3941604887},
{"learn":[3.999811484],"iteration":464,"passed_time":0.3420438597,"remaining_time":0.3935343332},
{"learn":[3.997483319],"iteration":465,"passed_time":0.3429695334,"remaining_time":0.3930165898},
{"learn":[3.99708333],"iteration":466,"passed_time":0.3438131928,"remaining_time":0.3924034942},
{"learn":[3.995860263],"iteration":467,"passed_time":0.3444830397,"remaining_time":0.3915918315},
{"learn":[3.994131111],"iteration":468,"passed_time":0.3451066641,"remaining_time":0.3907284406},
{"learn":[3.993125499],"iteration":469,"passed_time":0.3457409521,"remaining_time":0.3898780949},
{"learn":[3.992954084],"iteration":470,"passed_time":0.346390372,"remaining_time":0.389045662},
{"learn":[3.990635743],"iteration":471,"passed_time":0.34701844,"remaining_time":0.3881901193},
{"learn":[3.986678254],"iteration":472,"passed_time":0.3476564447,"remaining_time":0.3873466097},
{"learn":[3.986393291],"iteration":473,"passed_time":0.3482528795,"remaining_time":0.3864578368},
{"learn":[3.986152671],"iteration":474,"passed_time":0.3488493861,"remaining_time":0.3855703741},
{"learn":[3.985596662],"iteration":475,"passed_time":0.3494475478,"remaining_time":0.3846859559},
{"learn":[3.983853457],"iteration":476,"passed_time":0.3504830717,"remaining_time":0.3842822778},
{"learn":[3.983263928],"iteration":477,"passed_time":0.351935182,"remaining_time":0.3843308891},
{"learn":[3.980067202],"iteration":478,"passed_time":0.3528940796,"remaining_time":0.3838367756},
{"learn":[3.978115407],"iteration":479,"passed_time":0.3535161894,"remaining_time":0.3829758718},
{"learn":[3.972661644],"iteration":480,"passed_time":0.3541803332,"remaining_time":0.3821613158},
{"learn":[3.969938254],"iteration":481,"passed_time":0.3548304106,"remaining_time":0.381332267},
{"learn":[3.968211434],"iteration":482,"passed_time":0.3554729607,"remaining_time":0.380495902},
{"learn":[3.966113368],"iteration":483,"passed_time":0.3561143475,"remaining_time":0.3796590977},
{"learn":[3.962246044],"iteration":484,"passed_time":0.356818381,"remaining_time":0.378889621},
{"learn":[3.961319703],"iteration":485,"passed_time":0.3574619154,"remaining_time":0.3780564291},
{"learn":[3.96078191],"iteration":486,"passed_time":0.3580671837,"remaining_time":0.3771837068},
{"learn":[3.958913633],"iteration":487,"passed_time":0.358739236,"remaining_time":0.3763821493},
{"learn":[3.957428286],"iteration":488,"passed_time":0.3594267437,"remaining_time":0.3755972721},
{"learn":[3.952641965],"iteration":489,"passed_time":0.3601270527,"remaining_time":0.3748261161},
{"learn":[3.951486786],"iteration":490,"passed_time":0.3608045536,"remaining_time":0.3740316045},
{"learn":[3.94938344],"iteration":491,"passed_time":0.3616533159,"remaining_time":0.3734143994},
{"learn":[3.947297924],"iteration":492,"passed_time":0.3624041228,"remaining_time":0.3726955178},
{"learn":[3.946284886],"iteration":493,"passed_time":0.3630084762,"remaining_time":0.3718264959},
{"learn":[3.943288204],"iteration":494,"passed_time":0.3636335362,"remaining_time":0.3709796682},
{"learn":[3.943076488],"iteration":495,"passed_time":0.3642328478,"remaining_time":0.3701075712},
{"learn":[3.942347078],"iteration":496,"passed_time":0.3648590906,"remaining_time":0.3692638281},
{"learn":[3.940251541],"iteration":497,"passed_time":0.3657747776,"remaining_time":0.3687127276},
{"learn":[3.939011019],"iteration":498,"passed_time":0.3670771934,"remaining_time":0.3685484447},
{"learn":[3.938760512],"iteration":499,"passed_time":0.368033107,"remaining_time":0.368033107},
{"learn":[3.934522727],"iteration":500,"passed_time":0.3686662728,"remaining_time":0.3671945512},
{"learn":[3.930091193],"iteration":501,"passed_time":0.3694017817,"remaining_time":0.3664583412},
{"learn":[3.927671752],"iteration":502,"passed_time":0.370057884,"remaining_time":0.3656436747},
{"learn":[3.927280041],"iteration":503,"passed_time":0.3707686983,"remaining_time":0.3648834809},
{"learn":[3.925987561],"iteration":504,"passed_time":0.3715237566,"remaining_time":0.3641668505},
{"learn":[3.921645957],"iteration":505,"passed_time":0.3722055039,"remaining_time":0.3633784959},
{"learn":[3.920333743],"iteration":506,"passed_time":0.3728251803,"remaining_time":0.3625302049},
{"learn":[3.918659461],"iteration":507,"passed_time":0.3734746196,"remaining_time":0.3617116395},
{"learn":[3.916124385],"iteration":508,"passed_time":0.3741114477,"remaining_time":0.3608815733},
{"learn":[3.913849268],"iteration":509,"passed_time":0.3747291694,"remaining_time":0.3600339078},
{"learn":[3.912826119],"iteration":510,"passed_time":0.3753803612,"remaining_time":0.3592191715},
{"learn":[3.910034145],"iteration":511,"passed_time":0.3760089155,"remaining_time":0.3583834976},
{"learn":[3.90792379],"iteration":512,"passed_time":0.3766784106,"remaining_time":0.357587497},
{"learn":[3.907823851],"iteration":513,"passed_time":0.3772866018,"remaining_time":0.3567340243},
{"learn":[3.904527401],"iteration":514,"passed_time":0.3779655962,"remaining_time":0.3559481829},
{"learn":[3.903378283],"iteration":515,"passed_time":0.378674284,"remaining_time":0.3551906075},
{"learn":[3.902170135],"iteration":516,"passed_time":0.3793862155,"remaining_time":0.3544362517},
{"learn":[3.899435429],"iteration":517,"passed_time":0.3802198816,"remaining_time":0.3537953338},
{"learn":[3.897497505],"iteration":518,"passed_time":0.381757386,"remaining_time":0.3538059781},
{"learn":[3.896426119],"iteration":519,"passed_time":0.382935759,"remaining_time":0.3534791622},
{"learn":[3.896044669],"iteration":520,"passed_time":0.383684147,"remaining_time":0.3527537551},
{"learn":[3.892795942],"iteration":521,"passed_time":0.3845038512,"remaining_time":0.3520935649},
{"learn":[3.892413888],"iteration":522,"passed_time":0.3851932958,"remaining_time":0.351313962},
{"learn":[3.891738985],"iteration":523,"passed_time":0.3859582574,"remaining_time":0.3506033025},
{"learn":[3.88822057],"iteration":524,"passed_time":0.3867433231,"remaining_time":0.3499106257},
{"learn":[3.883837053],"iteration":525,"passed_time":0.3874783467,"remaining_time":0.3491725026},
{"learn":[3.881769742],"iteration":526,"passed_time":0.3883332596,"remaining_time":0.3485419958},
{"learn":[3.880356898],"iteration":527,"passed_time":0.3891514119,"remaining_time":0.3478777773},
{"learn":[3.879250273],"iteration":528,"passed_time":0.3898268324,"remaining_time":0.3470858943},
{"learn":[3.877174493],"iteration":529,"passed_time":0.3905390724,"remaining_time":0.346327102},
{"learn":[3.875854201],"iteration":530,"passed_time":0.391297321,"remaining_time":0.3456091215},
{"learn":[3.873189396],"iteration":531,"passed_time":0.3920024305,"remaining_time":0.3448442434},
{"learn":[3.871583368],"iteration":532,"passed_time":0.3926545994,"remaining_time":0.3440332044},
{"learn":[3.869622679],"iteration":533,"passed_time":0.3933396677,"remaining_time":0.3432514703},
{"learn":[3.866860164],"iteration":534,"passed_time":0.394010779,"remaining_time":0.3424579668},
{"learn":[3.864498444],"iteration":535,"passed_time":0.3947385171,"remaining_time":0.3417139402},
{"learn":[3.861416322],"iteration":536,"passed_time":0.3957934994,"remaining_time":0.3412521233},
{"learn":[3.860265769],"iteration":537,"passed_time":0.4146014708,"remaining_time":0.3560332333},
{"learn":[3.859328725],"iteration":538,"passed_time":0.4164653529,"remaining_time":0.3561976395},
{"learn":[3.858521278],"iteration":539,"passed_time":0.4184018728,"remaining_time":0.3564164102},
{"learn":[3.85599111],"iteration":540,"passed_time":0.4201247555,"remaining_time":0.3564459571},
{"learn":[3.852379816],"iteration":541,"passed_time":0.4215735231,"remaining_time":0.3562374051},
{"learn":[3.851327537],"iteration":542,"passed_time":0.4229663376,"remaining_time":0.3559771939},
{"learn":[3.847854898],"iteration":543,"passed_time":0.4243295282,"remaining_time":0.3556879869},
{"learn":[3.847083414],"iteration":544,"passed_time":0.4257029228,"remaining_time":0.3554033576},
{"learn":[3.845397429],"iteration":545,"passed_time":0.4271307493,"remaining_time":0.3551600003},
{"learn":[3.841933528],"iteration":546,"passed_time":0.4298997346,"remaining_time":0.3560229978},
{"learn":[3.840996474],"iteration":547,"passed_time":0.4313165828,"remaining_time":0.3557574734},
{"learn":[3.838355966],"iteration":548,"passed_time":0.4326853398,"remaining_time":0.3554482482},
{"learn":[3.83342799],"iteration":549,"passed_time":0.4337827529,"remaining_time":0.3549131614},
{"learn":[3.828161535],"iteration":550,"passed_time":0.4350286381,"remaining_time":0.3544970209},
{"learn":[3.823502399],"iteration":551,"passed_time":0.4363763467,"remaining_time":0.3541605133},
{"learn":[3.820068862],"iteration":552,"passed_time":0.4374851438,"remaining_time":0.353627232},
{"learn":[3.817951642],"iteration":553,"passed_time":0.4387867599,"remaining_time":0.3532471027},
{"learn":[3.815785958],"iteration":554,"passed_time":0.4398447185,"remaining_time":0.3526682878},
{"learn":[3.81503012],"iteration":555,"passed_time":0.4407957731,"remaining_time":0.35200238},
{"learn":[3.813529315],"iteration":556,"passed_time":0.4415876586,"remaining_time":0.3512088559},
{"learn":[3.808881326],"iteration":557,"passed_time":0.4427978227,"remaining_time":0.3507466624},
{"learn":[3.808740434],"iteration":558,"passed_time":0.4444331141,"remaining_time":0.3506171795},
{"learn":[3.80714352],"iteration":559,"passed_time":0.4452659659,"remaining_time":0.3498518303},
{"learn":[3.80573346],"iteration":560,"passed_time":0.4459737794,"remaining_time":0.3489883942},
{"learn":[3.803370052],"iteration":561,"passed_time":0.4466643245,"remaining_time":0.3481120537},
{"learn":[3.803215211],"iteration":562,"passed_time":0.4473494639,"remaining_time":0.3472321772},
{"learn":[3.801309667],"iteration":563,"passed_time":0.4480532712,"remaining_time":0.3463674224},
{"learn":[3.800003847],"iteration":564,"passed_time":0.4487377047,"remaining_time":0.3454883213},
{"learn":[3.798026138],"iteration":565,"passed_time":0.449420707,"remaining_time":0.3446088107},
{"learn":[3.794745847],"iteration":566,"passed_time":0.4501028906,"remaining_time":0.343729368},
{"learn":[3.794312041],"iteration":567,"passed_time":0.4507576507,"remaining_time":0.3428297625},
{"learn":[3.792205926],"iteration":568,"passed_time":0.4514565952,"remaining_time":0.341964486},
{"learn":[3.788991061],"iteration":569,"passed_time":0.452097952,"remaining_time":0.3410563498},
{"learn":[3.787391572],"iteration":570,"passed_time":0.4527896532,"remaining_time":0.3401869724},
{"learn":[3.7826445],"iteration":571,"passed_time":0.4534756775,"remaining_time":0.3393139685},
{"learn":[3.781700331],"iteration":572,"passed_time":0.4541887261,"remaining_time":0.3384617558},
{"learn":[3.780045374],"iteration":573,"passed_time":0.4548869098,"remaining_time":0.3375989957},
{"learn":[3.775462644],"iteration":574,"passed_time":0.4555614099,"remaining_time":0.336719303},
{"learn":[3.773711943],"iteration":575,"passed_time":0.4562483895,"remaining_time":0.335849509},
{"learn":[3.772415806],"iteration":576,"passed_time":0.4568751475,"remaining_time":0.3349362},
{"learn":[3.770170875],"iteration":577,"passed_time":0.457836324,"remaining_time":0.3342680428},
{"learn":[3.765166479],"iteration":578,"passed_time":0.4592650325,"remaining_time":0.3339388233},
{"learn":[3.763976102],"iteration":579,"passed_time":0.460117552,"remaining_time":0.3331885722},
{"learn":[3.760761708],"iteration":580,"passed_time":0.4607683531,"remaining_time":0.3322924956},
{"learn":[3.758155662],"iteration":581,"passed_time":0.4614287096,"remaining_time":0.3314041248},
{"learn":[3.756844548],"iteration":582,"passed_time":0.462205521,"remaining_time":0.3305998324},
{"learn":[3.753098923],"iteration":583,"passed_time":0.4629608333,"remaining_time":0.3297803196},
{"learn":[3.751618946],"iteration":584,"passed_time":0.463711116,"remaining_time":0.3289574584},
{"learn":[3.751398464],"iteration":585,"passed_time":0.4643768916,"remaining_time":0.3280751419},
{"learn":[3.749920103],"iteration":586,"passed_time":0.4649680363,"remaining_time":0.3271410545},
{"learn":[3.748237465],"iteration":587,"passed_time":0.4655896297,"remaining_time":0.3262294684},
{"learn":[3.746021536],"iteration":588,"passed_time":0.4662309348,"remaining_time":0.3253326217},
{"learn":[3.74417648],"iteration":589,"passed_time":0.466833648,"remaining_time":0.3244098232},
{"learn":[3.738788389],"iteration":590,"passed_time":0.4674700981,"remaining_time":0.3235114554},
{"learn":[3.736021611],"iteration":591,"passed_time":0.4681027482,"remaining_time":0.3226113535},
{"learn":[3.734546151],"iteration":592,"passed_time":0.4687359952,"remaining_time":0.3217125633},
{"learn":[3.733527479],"iteration":593,"passed_time":0.4694738701,"remaining_time":0.3208861806},
{"learn":[3.733026392],"iteration":594,"passed_time":0.4701285457,"remaining_time":0.3200034639},
{"learn":[3.730314752],"iteration":595,"passed_time":0.4707749103,"remaining_time":0.3191158788},
{"learn":[3.727342596],"iteration":596,"passed_time":0.4714443693,"remaining_time":0.3182446915},
{"learn":[3.725459604],"iteration":597,"passed_time":0.4721954835,"remaining_time":0.3174290709},
{"learn":[3.723158842],"iteration":598,"passed_time":0.4731179158,"remaining_time":0.3167283543},
{"learn":[3.722362756],"iteration":599,"passed_time":0.4749486478,"remaining_time":0.3166324319},
{"learn":[3.721443615],"iteration":600,"passed_time":0.4756962077,"remaining_time":0.3158116254},
{"learn":[3.720743486],"iteration":601,"passed_time":0.4764061027,"remaining_time":0.3149661609},
{"learn":[3.720215334],"iteration":602,"passed_time":0.4771310162,"remaining_time":0.3141310339},
{"learn":[3.719436563],"iteration":603,"passed_time":0.4778882927,"remaining_time":0.3133174899},
{"learn":[3.715046574],"iteration":604,"passed_time":0.4787659647,"remaining_time":0.3125827373},
{"learn":[3.71443396],"iteration":605,"passed_time":0.4794520211,"remaining_time":0.3117229312},
{"learn":[3.712938941],"iteration":606,"passed_time":0.4801851122,"remaining_time":0.3108941501},
{"learn":[3.712814764],"iteration":607,"passed_time":0.4808619262,"remaining_time":0.3100293998},
{"learn":[3.71235348],"iteration":608,"passed_time":0.4816150541,"remaining_time":0.309214263},
{"learn":[3.711223749],"iteration":609,"passed_time":0.4822863811,"remaining_time":0.3083470305},
{"learn":[3.710755648],"iteration":610,"passed_time":0.4829698803,"remaining_time":0.3074881889},
{"learn":[3.708668039],"iteration":611,"passed_time":0.4836278402,"remaining_time":0.3066137287},
{"learn":[3.705623591],"iteration":612,"passed_time":0.4842789575,"remaining_time":0.3057356551},
{"learn":[3.704045802],"iteration":613,"passed_time":0.4849087485,"remaining_time":0.3048449135},
{"learn":[3.699915209],"iteration":614,"passed_time":0.4855616444,"remaining_time":0.3039694847},
{"learn":[3.696182221],"iteration":615,"passed_time":0.4862462102,"remaining_time":0.3031145206},
{"learn":[3.694263278],"iteration":616,"passed_time":0.4868758439,"remaining_time":0.3022260101},
{"learn":[3.693810229],"iteration":617,"passed_time":0.487697315,"remaining_time":0.3014569164},
{"learn":[3.690900932],"iteration":618,"passed_time":0.4892201072,"remaining_time":0.3011193228},
{"learn":[3.688020895],"iteration":619,"passed_time":0.4902245604,"remaining_time":0.3004602145},
{"learn":[3.685491894],"iteration":620,"passed_time":0.4909166885,"remaining_time":0.29960938},
{"learn":[3.684328128],"iteration":621,"passed_time":0.4915949187,"remaining_time":0.2987506097},
{"learn":[3.680640153],"iteration":622,"passed_time":0.4922419036,"remaining_time":0.2978735115},
{"learn":[3.678932783],"iteration":623,"passed_time":0.4929259764,"remaining_time":0.2970194986},
{"learn":[3.674167041],"iteration":624,"passed_time":0.4935605745,"remaining_time":0.2961363447},
{"learn":[3.672200976],"iteration":625,"passed_time":0.4941895213,"remaining_time":0.2952506086},
{"learn":[3.670606604],"iteration":626,"passed_time":0.4948265022,"remaining_time":0.294370471},
{"learn":[3.665506042],"iteration":627,"passed_time":0.4954614105,"remaining_time":0.2934898801},
{"learn":[3.664214007],"iteration":628,"passed_time":0.4961166453,"remaining_time":0.2926220595},
{"learn":[3.66261643],"iteration":629,"passed_time":0.4967552408,"remaining_time":0.2917451414},
{"learn":[3.662118449],"iteration":630,"passed_time":0.4974081306,"remaining_time":0.2908773379},
{"learn":[3.660871366],"iteration":631,"passed_time":0.4982785577,"remaining_time":0.2901368817},
{"learn":[3.656695243],"iteration":632,"passed_time":0.4989944204,"remaining_time":0.2893064017},
{"learn":[3.654497801],"iteration":633,"passed_time":0.4996769119,"remaining_time":0.2884570186},
{"learn":[3.654189134],"iteration":634,"passed_time":0.5003005735,"remaining_time":0.2875743454},
{"learn":[3.653957699],"iteration":635,"passed_time":0.5008904337,"remaining_time":0.2866731413},
{"learn":[3.651920725],"iteration":636,"passed_time":0.501512624,"remaining_time":0.2857913383},
{"learn":[3.65106705],"iteration":637,"passed_time":0.5021402263,"remaining_time":0.2849134199},
{"learn":[3.650612844],"iteration":638,"passed_time":0.5029236835,"remaining_time":0.2841243345},
{"learn":[3.649884732],"iteration":639,"passed_time":0.5041141809,"remaining_time":0.2835642268},
{"learn":[3.646276182],"iteration":640,"passed_time":0.5050589294,"remaining_time":0.2828645174},
{"learn":[3.645808194],"iteration":641,"passed_time":0.5057268054,"remaining_time":0.2820096516},
{"learn":[3.645042989],"iteration":642,"passed_time":0.5063619927,"remaining_time":0.2811372184},
{"learn":[3.639864499],"iteration":643,"passed_time":0.5070535439,"remaining_time":0.2802966795},
{"learn":[3.637318478],"iteration":644,"passed_time":0.5077443825,"remaining_time":0.2794562105},
{"learn":[3.636344905],"iteration":645,"passed_time":0.5084256457,"remaining_time":0.2786109576},
{"learn":[3.634754643],"iteration":646,"passed_time":0.5091432703,"remaining_time":0.2777860501},
{"learn":[3.630724975],"iteration":647,"passed_time":0.5098013614,"remaining_time":0.2769291346},
{"learn":[3.629408252],"iteration":648,"passed_time":0.5104105659,"remaining_time":0.2760463923},
{"learn":[3.62790646],"iteration":649,"passed_time":0.5110279135,"remaining_time":0.2751688765},
{"learn":[3.627388973],"iteration":650,"passed_time":0.5116973735,"remaining_time":0.2743200973},
{"learn":[3.625163557],"iteration":651,"passed_time":0.5123128253,"remaining_time":0.2734430417},
{"learn":[3.623701985],"iteration":652,"passed_time":0.5129516337,"remaining_time":0.2725791989},
{"learn":[3.622342639],"iteration":653,"passed_time":0.5136234765,"remaining_time":0.2717335212},
{"learn":[3.621130639],"iteration":654,"passed_time":0.5143017233,"remaining_time":0.2708917474},
{"learn":[3.619125665],"iteration":655,"passed_time":0.5149285769,"remaining_time":0.270023522},
{"learn":[3.618878783],"iteration":656,"passed_time":0.515543086,"remaining_time":0.2691495867},
{"learn":[3.616207429],"iteration":657,"passed_time":0.5162454381,"remaining_time":0.268322097},
{"learn":[3.61206486],"iteration":658,"passed_time":0.5169453598,"remaining_time":0.2674937294},
{"learn":[3.611955873],"iteration":659,"passed_time":0.5177288987,"remaining_time":0.2667088266},
{"learn":[3.610713743],"iteration":660,"passed_time":0.5190977918,"remaining_time":0.2662241323},
{"learn":[3.610044025],"iteration":661,"passed_time":0.5201588718,"remaining_time":0.2655796052},
{"learn":[3.607342669],"iteration":662,"passed_time":0.5208572672,"remaining_time":0.2647494706},
{"learn":[3.602510618],"iteration":663,"passed_time":0.5216500875,"remaining_time":0.2639675142},
{"learn":[3.600492392],"iteration":664,"passed_time":0.5223874555,"remaining_time":0.2631575904},
{"learn":[3.597171065],"iteration":665,"passed_time":0.5230855296,"remaining_time":0.2623281785},
{"learn":[3.594358798],"iteration":666,"passed_time":0.5237053911,"remaining_time":0.2614601128},
{"learn":[3.593945251],"iteration":667,"passed_time":0.5242970855,"remaining_time":0.260578791},
{"learn":[3.593607748],"iteration":668,"passed_time":0.5249512981,"remaining_time":0.2597292671},
{"learn":[3.592238714],"iteration":669,"passed_time":0.5256688694,"remaining_time":0.2589115327},
{"learn":[3.590144654],"iteration":670,"passed_time":0.5264402828,"remaining_time":0.2581204963},
{"learn":[3.587151536],"iteration":671,"passed_time":0.5271976131,"remaining_time":0.2573226445},
{"learn":[3.586070865],"iteration":672,"passed_time":0.5278205888,"remaining_time":0.2564596323},
{"learn":[3.585102746],"iteration":673,"passed_time":0.5284768068,"remaining_time":0.255613411},
{"learn":[3.584362847],"iteration":674,"passed_time":0.5290869328,"remaining_time":0.2547455602},
{"learn":[3.581407561],"iteration":675,"passed_time":0.5297097968,"remaining_time":0.2538845772},
{"learn":[3.57919422],"iteration":676,"passed_time":0.5303163673,"remaining_time":0.2530165238},
{"learn":[3.577632204],"iteration":677,"passed_time":0.5309481259,"remaining_time":0.2521612043},
{"learn":[3.573911195],"iteration":678,"passed_time":0.5315601344,"remaining_time":0.2512972064},
{"learn":[3.573408216],"iteration":679,"passed_time":0.5322885494,"remaining_time":0.2504887292},
{"learn":[3.571076482],"iteration":680,"passed_time":0.5332527545,"remaining_time":0.2497909379},
{"learn":[3.568177107],"iteration":681,"passed_time":0.5349995103,"remaining_time":0.2494572496},
{"learn":[3.564824621],"iteration":682,"passed_time":0.5359012748,"remaining_time":0.2487272388},
{"learn":[3.562475026],"iteration":683,"passed_time":0.5367033338,"remaining_time":0.247950663},
{"learn":[3.561226889],"iteration":684,"passed_time":0.5375167879,"remaining_time":0.2471792528},
{"learn":[3.559383467],"iteration":685,"passed_time":0.5381807616,"remaining_time":0.246339299},
{"learn":[3.555209766],"iteration":686,"passed_time":0.5388215703,"remaining_time":0.2454893035},
{"learn":[3.55345383],"iteration":687,"passed_time":0.5395399814,"remaining_time":0.2446751079},
{"learn":[3.552300968],"iteration":688,"passed_time":0.5401899305,"remaining_time":0.2438302879},
{"learn":[3.551253986],"iteration":689,"passed_time":0.540856746,"remaining_time":0.2429936105},
{"learn":[3.549807725],"iteration":690,"passed_time":0.5415038165,"remaining_time":0.2421485952},
{"learn":[3.547992926],"iteration":691,"passed_time":0.5421193711,"remaining_time":0.2412901247},
{"learn":[3.545438607],"iteration":692,"passed_time":0.5427873505,"remaining_time":0.2404555795},
{"learn":[3.543313763],"iteration":693,"passed_time":0.5434320643,"remaining_time":0.239611256},
{"learn":[3.542962896],"iteration":694,"passed_time":0.5440548099,"remaining_time":0.2387578662},
{"learn":[3.539800465],"iteration":695,"passed_time":0.5446633658,"remaining_time":0.2378989414},
{"learn":[3.53953187],"iteration":696,"passed_time":0.5453071181,"remaining_time":0.2370560356},
{"learn":[3.536332425],"iteration":697,"passed_time":0.5459726508,"remaining_time":0.236223124},
{"learn":[3.534993327],"iteration":698,"passed_time":0.5466365956,"remaining_time":0.2353900076},
{"learn":[3.531637011],"iteration":699,"passed_time":0.5472684209,"remaining_time":0.234543609},
{"learn":[3.531040284],"iteration":700,"passed_time":0.5481866335,"remaining_time":0.2338199763},
{"learn":[3.529973872],"iteration":701,"passed_time":0.54995963,"remaining_time":0.2334586463},
{"learn":[3.527325183],"iteration":702,"passed_time":0.5508303511,"remaining_time":0.2327121113},
{"learn":[3.527200815],"iteration":703,"passed_time":0.5515432097,"remaining_time":0.2318988495},
{"learn":[3.523459911],"iteration":704,"passed_time":0.5523464525,"remaining_time":0.2311236929},
{"learn":[3.522729934],"iteration":705,"passed_time":0.5532076493,"remaining_time":0.2303725905},
{"learn":[3.522260582],"iteration":706,"passed_time":0.5539775537,"remaining_time":0.2295833426},
{"learn":[3.518641591],"iteration":707,"passed_time":0.5546614475,"remaining_time":0.2287586761},
{"learn":[3.516856405],"iteration":708,"passed_time":0.5552907816,"remaining_time":0.2279120133},
{"learn":[3.515083413],"iteration":709,"passed_time":0.5559183811,"remaining_time":0.2270652542},
{"learn":[3.514671214],"iteration":710,"passed_time":0.5565157324,"remaining_time":0.2262068167},
{"learn":[3.512617621],"iteration":711,"passed_time":0.5571200208,"remaining_time":0.2253519185},
{"learn":[3.510747971],"iteration":712,"passed_time":0.5577524758,"remaining_time":0.2245090611},
{"learn":[3.508149266],"iteration":713,"passed_time":0.5583849691,"remaining_time":0.2236668084},
{"learn":[3.504557165],"iteration":714,"passed_time":0.5590249692,"remaining_time":0.2228281346},
{"learn":[3.501367208],"iteration":715,"passed_time":0.5596777778,"remaining_time":0.2219950962},
{"learn":[3.497593362],"iteration":716,"passed_time":0.5603505622,"remaining_time":0.221170445},
{"learn":[3.496291169],"iteration":717,"passed_time":0.5609880228,"remaining_time":0.2203323432},
{"learn":[3.49330374],"iteration":718,"passed_time":0.5616731116,"remaining_time":0.2195134136},
{"learn":[3.490044385],"iteration":719,"passed_time":0.56245319,"remaining_time":0.2187317961},
{"learn":[3.488891789],"iteration":720,"passed_time":0.5634100529,"remaining_time":0.2180185919},
{"learn":[3.486869081],"iteration":721,"passed_time":0.5652757124,"remaining_time":0.2176546372},
{"learn":[3.486303638],"iteration":722,"passed_time":0.5660544747,"remaining_time":0.2168701099},
{"learn":[3.486035862],"iteration":723,"passed_time":0.5667438688,"remaining_time":0.2160515301},
{"learn":[3.482668951],"iteration":724,"passed_time":0.5675030917,"remaining_time":0.2152597934},
{"learn":[3.47820549],"iteration":725,"passed_time":0.5683813273,"remaining_time":0.2145130629},
{"learn":[3.474392283],"iteration":726,"passed_time":0.5691469653,"remaining_time":0.2137236885},
{"learn":[3.472268163],"iteration":727,"passed_time":0.5698456502,"remaining_time":0.2129093638},
{"learn":[3.471209164],"iteration":728,"passed_time":0.5706172832,"remaining_time":0.2121224743},
{"learn":[3.470049971],"iteration":729,"passed_time":0.5712653986,"remaining_time":0.211289942},
{"learn":[3.469078654],"iteration":730,"passed_time":0.5719468308,"remaining_time":0.2104701744},
{"learn":[3.468643292],"iteration":731,"passed_time":0.5725868108,"remaining_time":0.2096356083},
{"learn":[3.468134848],"iteration":732,"passed_time":0.5731887476,"remaining_time":0.2087877157},
{"learn":[3.467820182],"iteration":733,"passed_time":0.5737711855,"remaining_time":0.2079334269},
{"learn":[3.465776156],"iteration":734,"passed_time":0.5743939578,"remaining_time":0.2070944201},
{"learn":[3.463037608],"iteration":735,"passed_time":0.5750204045,"remaining_time":0.206257319},
{"learn":[3.45965637],"iteration":736,"passed_time":0.5756567724,"remaining_time":0.2054243299},
{"learn":[3.457275091],"iteration":737,"passed_time":0.5762966718,"remaining_time":0.2045931274},
{"learn":[3.455522955],"iteration":738,"passed_time":0.5769110509,"remaining_time":0.2037534293},
{"learn":[3.451270508],"iteration":739,"passed_time":0.5775409553,"remaining_time":0.2029197951},
{"learn":[3.450978947],"iteration":740,"passed_time":0.5784816925,"remaining_time":0.2021953554},
{"learn":[3.450608492],"iteration":741,"passed_time":0.5804686502,"remaining_time":0.2018341129},
{"learn":[3.448122004],"iteration":742,"passed_time":0.5813282079,"remaining_time":0.2010785322},
{"learn":[3.445646714],"iteration":743,"passed_time":0.5821830624,"remaining_time":0.2003210537},
{"learn":[3.44411263],"iteration":744,"passed_time":0.5830195742,"remaining_time":0.1995570355},
{"learn":[3.443264164],"iteration":745,"passed_time":0.5837113994,"remaining_time":0.1987435596},
{"learn":[3.439521363],"iteration":746,"passed_time":0.5843939804,"remaining_time":0.1979272785},
{"learn":[3.436809225],"iteration":747,"passed_time":0.5850412876,"remaining_time":0.1970994712},
{"learn":[3.435509465],"iteration":748,"passed_time":0.5856743518,"remaining_time":0.1962673729},
{"learn":[3.434450277],"iteration":749,"passed_time":0.5863291986,"remaining_time":0.1954430662},
{"learn":[3.431786753],"iteration":750,"passed_time":0.5869816432,"remaining_time":0.1946184143},
{"learn":[3.430150302],"iteration":751,"passed_time":0.587620491,"remaining_time":0.1937897364},
{"learn":[3.42696281],"iteration":752,"passed_time":0.5882717757,"remaining_time":0.1929656422},
{"learn":[3.426870334],"iteration":753,"passed_time":0.588925323,"remaining_time":0.1921427446},
{"learn":[3.425200309],"iteration":754,"passed_time":0.5896144347,"remaining_time":0.1913318364},
{"learn":[3.423383783],"iteration":755,"passed_time":0.5902706154,"remaining_time":0.1905106219},
{"learn":[3.422752979],"iteration":756,"passed_time":0.5909081872,"remaining_time":0.1896838699},
{"learn":[3.420845924],"iteration":757,"passed_time":0.5915566428,"remaining_time":0.1888610917},
{"learn":[3.418917862],"iteration":758,"passed_time":0.5922097593,"remaining_time":0.188040253},
{"learn":[3.417095735],"iteration":759,"passed_time":0.5928397287,"remaining_time":0.1872125459},
{"learn":[3.414391848],"iteration":760,"passed_time":0.5937238031,"remaining_time":0.1864651629},
{"learn":[3.41426711],"iteration":761,"passed_time":0.5959042845,"remaining_time":0.1861223356},
{"learn":[3.411976013],"iteration":762,"passed_time":0.5967985346,"remaining_time":0.1853751674},
{"learn":[3.408614844],"iteration":763,"passed_time":0.5975206435,"remaining_time":0.1845744396},
{"learn":[3.407906721],"iteration":764,"passed_time":0.5983119214,"remaining_time":0.1837951654},
{"learn":[3.407494015],"iteration":765,"passed_time":0.5993616752,"remaining_time":0.1830948198},
{"learn":[3.406287128],"iteration":766,"passed_time":0.6001437695,"remaining_time":0.1823122533},
{"learn":[3.404600442],"iteration":767,"passed_time":0.6008149648,"remaining_time":0.1814961873},
{"learn":[3.404012662],"iteration":768,"passed_time":0.6014766108,"remaining_time":0.1806776295},
{"learn":[3.400398762],"iteration":769,"passed_time":0.6021007626,"remaining_time":0.1798482797},
{"learn":[3.399737714],"iteration":770,"passed_time":0.6028037234,"remaining_time":0.1790428698},
{"learn":[3.399185251],"iteration":771,"passed_time":0.603417297,"remaining_time":0.1782113261},
{"learn":[3.397245411],"iteration":772,"passed_time":0.604069979,"remaining_time":0.1773918308},
{"learn":[3.396229831],"iteration":773,"passed_time":0.6047202904,"remaining_time":0.1765720744},
{"learn":[3.394002836],"iteration":774,"passed_time":0.6053740189,"remaining_time":0.1757537474},
{"learn":[3.389617243],"iteration":775,"passed_time":0.6059879238,"remaining_time":0.1749243491},
{"learn":[3.385426488],"iteration":776,"passed_time":0.6066033172,"remaining_time":0.1740959327},
{"learn":[3.385072258],"iteration":777,"passed_time":0.6072951791,"remaining_time":0.173289884},
{"learn":[3.383842366],"iteration":778,"passed_time":0.6080182361,"remaining_time":0.1724929784},
{"learn":[3.380110746],"iteration":779,"passed_time":0.6092186019,"remaining_time":0.1718308877},
{"learn":[3.378595218],"iteration":780,"passed_time":0.6111143606,"remaining_time":0.1713624135},
{"learn":[3.377371219],"iteration":781,"passed_time":0.611897013,"remaining_time":0.1705799857},
{"learn":[3.375814782],"iteration":782,"passed_time":0.6126699082,"remaining_time":0.1697948532},
{"learn":[3.374195887],"iteration":783,"passed_time":0.6135075127,"remaining_time":0.16902758},
{"learn":[3.373704309],"iteration":784,"passed_time":0.6141613073,"remaining_time":0.1682097848},
{"learn":[3.372971757],"iteration":785,"passed_time":0.6148087858,"remaining_time":0.1673906872},
{"learn":[3.371565136],"iteration":786,"passed_time":0.6154371722,"remaining_time":0.1665668586},
{"learn":[3.3700309],"iteration":787,"passed_time":0.6161150967,"remaining_time":0.1657568534},
{"learn":[3.368186663],"iteration":788,"passed_time":0.6167711462,"remaining_time":0.1649413332},
{"learn":[3.366710398],"iteration":789,"passed_time":0.6174283969,"remaining_time":0.1641265359},
{"learn":[3.364598042],"iteration":790,"passed_time":0.6180979748,"remaining_time":0.1633153941},
{"learn":[3.36348442],"iteration":791,"passed_time":0.6187460046,"remaining_time":0.1624989507},
{"learn":[3.362001759],"iteration":792,"passed_time":0.6193764959,"remaining_time":0.1616783539},
{"learn":[3.361580401],"iteration":793,"passed_time":0.620048461,"remaining_time":0.1608689962},
{"learn":[3.359543675],"iteration":794,"passed_time":0.620730643,"remaining_time":0.1600626186},
{"learn":[3.35766119],"iteration":795,"passed_time":0.6213612471,"remaining_time":0.1592433347},
{"learn":[3.354592969],"iteration":796,"passed_time":0.6219742427,"remaining_time":0.1584200392},
{"learn":[3.350985986],"iteration":797,"passed_time":0.6226319375,"remaining_time":0.1576085857},
{"learn":[3.349589624],"iteration":798,"passed_time":0.6234333078,"remaining_time":0.1568336607},
{"learn":[3.349110856],"iteration":799,"passed_time":0.6243403803,"remaining_time":0.1560850951},
{"learn":[3.345315441],"iteration":800,"passed_time":0.6256919618,"remaining_time":0.1554465673},
{"learn":[3.34397474],"iteration":801,"passed_time":0.6264686792,"remaining_time":0.1546643373},
{"learn":[3.343800902],"iteration":802,"passed_time":0.627185603,"remaining_time":0.1538674518},
{"learn":[3.342329465],"iteration":803,"passed_time":0.6278455154,"remaining_time":0.1530568669},
{"learn":[3.34220347],"iteration":804,"passed_time":0.628429693,"remaining_time":0.1522283107},
{"learn":[3.341279219],"iteration":805,"passed_time":0.629090259,"remaining_time":0.1514187472},
{"learn":[3.337329521],"iteration":806,"passed_time":0.6297467182,"remaining_time":0.1506085708},
{"learn":[3.336708453],"iteration":807,"passed_time":0.6304011754,"remaining_time":0.1497982991},
{"learn":[3.333252703],"iteration":808,"passed_time":0.6310474972,"remaining_time":0.1489864919},
{"learn":[3.332186769],"iteration":809,"passed_time":0.631753521,"remaining_time":0.1481890975},
{"learn":[3.330594851],"iteration":810,"passed_time":0.6324970151,"remaining_time":0.1474006607},
{"learn":[3.327867442],"iteration":811,"passed_time":0.6332782058,"remaining_time":0.1466210624},
{"learn":[3.327563111],"iteration":812,"passed_time":0.6339977185,"remaining_time":0.1458272735},
{"learn":[3.326308994],"iteration":813,"passed_time":0.6347256272,"remaining_time":0.1450355856},
{"learn":[3.326249879],"iteration":814,"passed_time":0.6354358385,"remaining_time":0.144240037},
{"learn":[3.322336238],"iteration":815,"passed_time":0.6361426649,"remaining_time":0.1434439342},
{"learn":[3.320491154],"iteration":816,"passed_time":0.6368578479,"remaining_time":0.1426499219},
{"learn":[3.320434271],"iteration":817,"passed_time":0.6375269127,"remaining_time":0.1418458412},
{"learn":[3.319609638],"iteration":818,"passed_time":0.6381587458,"remaining_time":0.141033862},
{"learn":[3.316182682],"iteration":819,"passed_time":0.6390232963,"remaining_time":0.1402734065},
{"learn":[3.313126612],"iteration":820,"passed_time":0.6401106399,"remaining_time":0.1395612723},
{"learn":[3.311222803],"iteration":821,"passed_time":0.6410055836,"remaining_time":0.1388065619},
{"learn":[3.309627335],"iteration":822,"passed_time":0.6416926389,"remaining_time":0.1380068008},
{"learn":[3.307974895],"iteration":823,"passed_time":0.6423473689,"remaining_time":0.1372004089},
{"learn":[3.307321505],"iteration":824,"passed_time":0.6429748272,"remaining_time":0.1363885997},
{"learn":[3.306759087],"iteration":825,"passed_time":0.6437473183,"remaining_time":0.1356077886},
{"learn":[3.30484037],"iteration":826,"passed_time":0.6444144624,"remaining_time":0.1348049601},
{"learn":[3.30201994],"iteration":827,"passed_time":0.6450675872,"remaining_time":0.1339995471},
{"learn":[3.299302297],"iteration":828,"passed_time":0.6457343089,"remaining_time":0.1331973062},
{"learn":[3.298132671],"iteration":829,"passed_time":0.6464014673,"remaining_time":0.1323954813},
{"learn":[3.296976183],"iteration":830,"passed_time":0.6470314662,"remaining_time":0.1315864233},
{"learn":[3.293144745],"iteration":831,"passed_time":0.6476656853,"remaining_time":0.130778648},
{"learn":[3.290284404],"iteration":832,"passed_time":0.6483007137,"remaining_time":0.1299714516},
{"learn":[3.288285745],"iteration":833,"passed_time":0.6489125427,"remaining_time":0.1291600505},
{"learn":[3.286662667],"iteration":834,"passed_time":0.6495455646,"remaining_time":0.1283533152},
{"learn":[3.285692682],"iteration":835,"passed_time":0.6501766868,"remaining_time":0.1275466228},
{"learn":[3.284565611],"iteration":836,"passed_time":0.6507912398,"remaining_time":0.1267371232},
{"learn":[3.283897383],"iteration":837,"passed_time":0.651398126,"remaining_time":0.1259266067},
{"learn":[3.280712855],"iteration":838,"passed_time":0.6520396695,"remaining_time":0.1251232262},
{"learn":[3.280468341],"iteration":839,"passed_time":0.6526595377,"remaining_time":0.1243161024},
{"learn":[3.277814895],"iteration":840,"passed_time":0.6534032214,"remaining_time":0.1235328326},
{"learn":[3.276316385],"iteration":841,"passed_time":0.6543241963,"remaining_time":0.1227829252},
{"learn":[3.27557063],"iteration":842,"passed_time":0.6553310996,"remaining_time":0.1220486152},
{"learn":[3.27499628],"iteration":843,"passed_time":0.6564720613,"remaining_time":0.1213384379},
{"learn":[3.273569958],"iteration":844,"passed_time":0.6571494416,"remaining_time":0.1205422053},
{"learn":[3.269665595],"iteration":845,"passed_time":0.6577866549,"remaining_time":0.1197389419},
{"learn":[3.267984685],"iteration":846,"passed_time":0.6584791854,"remaining_time":0.118946063},
{"learn":[3.267702508],"iteration":847,"passed_time":0.6591161985,"remaining_time":0.1181434695},
{"learn":[3.266671924],"iteration":848,"passed_time":0.6597411985,"remaining_time":0.1173391295},
{"learn":[3.265359825],"iteration":849,"passed_time":0.660381781,"remaining_time":0.1165379614},
{"learn":[3.2618983],"iteration":850,"passed_time":0.661033373,"remaining_time":0.1157390982},
{"learn":[3.260456253],"iteration":851,"passed_time":0.6617234168,"remaining_time":0.1149472602},
{"learn":[3.258389147],"iteration":852,"passed_time":0.6623920276,"remaining_time":0.1141519672},
{"learn":[3.258108469],"iteration":853,"passed_time":0.6630442977,"remaining_time":0.1133541774},
{"learn":[3.256424936],"iteration":854,"passed_time":0.6636994413,"remaining_time":0.1125572152},
{"learn":[3.254817983],"iteration":855,"passed_time":0.6643496521,"remaining_time":0.1117597546},
{"learn":[3.253898449],"iteration":856,"passed_time":0.6650006677,"remaining_time":0.1109627719},
{"learn":[3.253023652],"iteration":857,"passed_time":0.6656553261,"remaining_time":0.1101667323},
{"learn":[3.252845542],"iteration":858,"passed_time":0.6663367065,"remaining_time":0.1093754082},
{"learn":[3.252316026],"iteration":859,"passed_time":0.666973768,"remaining_time":0.108577125},
{"learn":[3.24975301],"iteration":860,"passed_time":0.6676179422,"remaining_time":0.1077803647},
{"learn":[3.249151075],"iteration":861,"passed_time":0.6682635893,"remaining_time":0.1069841941},
{"learn":[3.246257135],"iteration":862,"passed_time":0.6689125195,"remaining_time":0.1061888936},
{"learn":[3.243826471],"iteration":863,"passed_time":0.6697270825,"remaining_time":0.1054200037},
{"learn":[3.243190653],"iteration":864,"passed_time":0.6706985291,"remaining_time":0.104675493},
{"learn":[3.24008797],"iteration":865,"passed_time":0.6715638083,"remaining_time":0.1039140304},
{"learn":[3.240036811],"iteration":866,"passed_time":0.6723810653,"remaining_time":0.1031449616},
{"learn":[3.238676314],"iteration":867,"passed_time":0.6732051858,"remaining_time":0.1023768255},
{"learn":[3.237848782],"iteration":868,"passed_time":0.6739772701,"remaining_time":0.1016007162},
{"learn":[3.236405498],"iteration":869,"passed_time":0.6748211513,"remaining_time":0.1008353444},
{"learn":[3.233378068],"iteration":870,"passed_time":0.6756399033,"remaining_time":0.1000660706},
{"learn":[3.233169169],"iteration":871,"passed_time":0.6763198359,"remaining_time":0.09927630619},
{"learn":[3.232434885],"iteration":872,"passed_time":0.6769530818,"remaining_time":0.0984800016},
{"learn":[3.229978115],"iteration":873,"passed_time":0.6775880446,"remaining_time":0.09768431765},
{"learn":[3.229648848],"iteration":874,"passed_time":0.6782071275,"remaining_time":0.09688673249},
{"learn":[3.227208761],"iteration":875,"passed_time":0.6788476255,"remaining_time":0.09609258626},
{"learn":[3.226258869],"iteration":876,"passed_time":0.6794962239,"remaining_time":0.0952999265},
{"learn":[3.225331995],"iteration":877,"passed_time":0.6802373236,"remaining_time":0.09452044816},
{"learn":[3.221968268],"iteration":878,"passed_time":0.6810379636,"remaining_time":0.09374925324},
{"learn":[3.221166317],"iteration":879,"passed_time":0.6817826771,"remaining_time":0.09297036507},
{"learn":[3.220047503],"iteration":880,"passed_time":0.682505289,"remaining_time":0.09218856912},
{"learn":[3.21982781],"iteration":881,"passed_time":0.6831058568,"remaining_time":0.09139057948},
{"learn":[3.216693405],"iteration":882,"passed_time":0.6837353588,"remaining_time":0.09059687087},
{"learn":[3.214798761],"iteration":883,"passed_time":0.6845374544,"remaining_time":0.0898261818},
{"learn":[3.214395085],"iteration":884,"passed_time":0.6857906836,"remaining_time":0.08911404363},
{"learn":[3.213470696],"iteration":885,"passed_time":0.6865150779,"remaining_time":0.08833263983},
{"learn":[3.211595017],"iteration":886,"passed_time":0.6872060483,"remaining_time":0.08754710649},
{"learn":[3.210965255],"iteration":887,"passed_time":0.6878383427,"remaining_time":0.08675438556},
{"learn":[3.209413583],"iteration":888,"passed_time":0.6884900186,"remaining_time":0.08596444551},
{"learn":[3.208331683],"iteration":889,"passed_time":0.6891313409,"remaining_time":0.08517353652},
{"learn":[3.207110711],"iteration":890,"passed_time":0.6898155482,"remaining_time":0.0843882096},
{"learn":[3.204519413],"iteration":891,"passed_time":0.6905072494,"remaining_time":0.08360401675},
{"learn":[3.201421296],"iteration":892,"passed_time":0.6911224594,"remaining_time":0.0828108658},
{"learn":[3.200691259],"iteration":893,"passed_time":0.6917605981,"remaining_time":0.08202083154},
{"learn":[3.200485067],"iteration":894,"passed_time":0.692375932,"remaining_time":0.0812284613},
{"learn":[3.197467568],"iteration":895,"passed_time":0.6930369799,"remaining_time":0.08044179231},
{"learn":[3.195838544],"iteration":896,"passed_time":0.6937440342,"remaining_time":0.0796606862},
{"learn":[3.195671746],"iteration":897,"passed_time":0.6943599662,"remaining_time":0.07886939482},
{"learn":[3.194213094],"iteration":898,"passed_time":0.6950167138,"remaining_time":0.07808307908},
{"learn":[3.192884691],"iteration":899,"passed_time":0.6956688355,"remaining_time":0.07729653728},
{"learn":[3.188364239],"iteration":900,"passed_time":0.6962791766,"remaining_time":0.07650570309},
{"learn":[3.185219478],"iteration":901,"passed_time":0.6969272047,"remaining_time":0.07571936371},
{"learn":[3.184120387],"iteration":902,"passed_time":0.697600332,"remaining_time":0.07493602681},
{"learn":[3.183725321],"iteration":903,"passed_time":0.69823072,"remaining_time":0.07414839504},
{"learn":[3.181264554],"iteration":904,"passed_time":0.698948727,"remaining_time":0.07337030836},
{"learn":[3.180741589],"iteration":905,"passed_time":0.6998776216,"remaining_time":0.07261423447},
{"learn":[3.179782639],"iteration":906,"passed_time":0.7008102519,"remaining_time":0.07185816254},
{"learn":[3.176377564],"iteration":907,"passed_time":0.7018359108,"remaining_time":0.07111112753},
{"learn":[3.174078182],"iteration":908,"passed_time":0.7025437805,"remaining_time":0.0703316656},
{"learn":[3.171242379],"iteration":909,"passed_time":0.7031732997,"remaining_time":0.06954461206},
{"learn":[3.170421012],"iteration":910,"passed_time":0.7038078512,"remaining_time":0.068758396},
{"learn":[3.170087224],"iteration":911,"passed_time":0.7044660106,"remaining_time":0.0679747905},
{"learn":[3.167303059],"iteration":912,"passed_time":0.7051371003,"remaining_time":0.06719269192},
{"learn":[3.16705966],"iteration":913,"passed_time":0.7057801017,"remaining_time":0.06640819338},
{"learn":[3.165667683],"iteration":914,"passed_time":0.706444255,"remaining_time":0.06562596904},
{"learn":[3.164689733],"iteration":915,"passed_time":0.7070868573,"remaining_time":0.06484202622},
{"learn":[3.163311455],"iteration":916,"passed_time":0.7077604081,"remaining_time":0.06406119288},
{"learn":[3.159425016],"iteration":917,"passed_time":0.7084922014,"remaining_time":0.06328579577},
{"learn":[3.159327058],"iteration":918,"passed_time":0.7092939741,"remaining_time":0.06251666148},
{"learn":[3.15819426],"iteration":919,"passed_time":0.710018543,"remaining_time":0.06174074287},
{"learn":[3.157086603],"iteration":920,"passed_time":0.7106317604,"remaining_time":0.06095538444},
{"learn":[3.153354154],"iteration":921,"passed_time":0.7112647723,"remaining_time":0.06017207401},
{"learn":[3.153261317],"iteration":922,"passed_time":0.7119122185,"remaining_time":0.05939029342},
{"learn":[3.153168454],"iteration":923,"passed_time":0.712539679,"remaining_time":0.05860715975},
{"learn":[3.152080399],"iteration":924,"passed_time":0.7131892884,"remaining_time":0.05782615852},
{"learn":[3.151635144],"iteration":925,"passed_time":0.7138046974,"remaining_time":0.057042708},
{"learn":[3.147762655],"iteration":926,"passed_time":0.7144655069,"remaining_time":0.05626319525},
{"learn":[3.147172317],"iteration":927,"passed_time":0.715532106,"remaining_time":0.05551542202},
{"learn":[3.146254125],"iteration":928,"passed_time":0.7164166162,"remaining_time":0.05475304601},
{"learn":[3.144869828],"iteration":929,"passed_time":0.7172220889,"remaining_time":0.0539844583},
{"learn":[3.143466218],"iteration":930,"passed_time":0.7178983042,"remaining_time":0.05320621159},
{"learn":[3.141919643],"iteration":931,"passed_time":0.7185503436,"remaining_time":0.05242641992},
{"learn":[3.141054135],"iteration":932,"passed_time":0.7192040571,"remaining_time":0.05164702232},
{"learn":[3.139390417],"iteration":933,"passed_time":0.7198752179,"remaining_time":0.05086912675},
{"learn":[3.139025283],"iteration":934,"passed_time":0.7204887338,"remaining_time":0.05008745208},
{"learn":[3.137824183],"iteration":935,"passed_time":0.7211329263,"remaining_time":0.04930823428},
{"learn":[3.135620453],"iteration":936,"passed_time":0.7217794855,"remaining_time":0.04852946381},
{"learn":[3.13443178],"iteration":937,"passed_time":0.7224328316,"remaining_time":0.04775142384},
{"learn":[3.132765713],"iteration":938,"passed_time":0.7230818491,"remaining_time":0.04697336826},
{"learn":[3.131434124],"iteration":939,"passed_time":0.7237264957,"remaining_time":0.04619530824},
{"learn":[3.128384262],"iteration":940,"passed_time":0.7243674918,"remaining_time":0.04541730288},
{"learn":[3.128120455],"iteration":941,"passed_time":0.7250623217,"remaining_time":0.04464290303},
{"learn":[3.126314615],"iteration":942,"passed_time":0.7257241644,"remaining_time":0.04386667802},
{"learn":[3.125409666],"iteration":943,"passed_time":0.7263972522,"remaining_time":0.04309136242},
{"learn":[3.123072589],"iteration":944,"passed_time":0.7271101341,"remaining_time":0.04231857924},
{"learn":[3.122921099],"iteration":945,"passed_time":0.7278644787,"remaining_time":0.04154828948},
{"learn":[3.122182662],"iteration":946,"passed_time":0.7285424554,"remaining_time":0.04077375938},
{"learn":[3.120040951],"iteration":947,"passed_time":0.729181385,"remaining_time":0.03999729116},
{"learn":[3.118767799],"iteration":948,"passed_time":0.7298377864,"remaining_time":0.03922205174},
{"learn":[3.118203218],"iteration":949,"passed_time":0.7307302217,"remaining_time":0.03845948536},
{"learn":[3.116343362],"iteration":950,"passed_time":0.7317506095,"remaining_time":0.03770323855},
{"learn":[3.11480829],"iteration":951,"passed_time":0.7324913996,"remaining_time":0.03693233947},
{"learn":[3.112607903],"iteration":952,"passed_time":0.7331702555,"remaining_time":0.03615844912},
{"learn":[3.111661241],"iteration":953,"passed_time":0.733798746,"remaining_time":0.03538232947},
{"learn":[3.110249676],"iteration":954,"passed_time":0.7344178527,"remaining_time":0.03460607683},
{"learn":[3.107333579],"iteration":955,"passed_time":0.7351070306,"remaining_time":0.03383337798},
{"learn":[3.107149851],"iteration":956,"passed_time":0.7357319905,"remaining_time":0.03305796823},
{"learn":[3.106867336],"iteration":957,"passed_time":0.7363883469,"remaining_time":0.03228424903},
{"learn":[3.10364681],"iteration":958,"passed_time":0.7370776037,"remaining_time":0.03151218118},
{"learn":[3.102703811],"iteration":959,"passed_time":0.7377416068,"remaining_time":0.03073923362},
{"learn":[3.101469264],"iteration":960,"passed_time":0.7383954226,"remaining_time":0.02996609936},
{"learn":[3.09863569],"iteration":961,"passed_time":0.739049852,"remaining_time":0.0291932374},
{"learn":[3.09645939],"iteration":962,"passed_time":0.7397040251,"remaining_time":0.02842061156},
{"learn":[3.096240186],"iteration":963,"passed_time":0.7403081139,"remaining_time":0.0276463611},
{"learn":[3.094838828],"iteration":964,"passed_time":0.7409314365,"remaining_time":0.02687316091},
{"learn":[3.094176802],"iteration":965,"passed_time":0.7415882075,"remaining_time":0.0261014483},
{"learn":[3.093182279],"iteration":966,"passed_time":0.7422497545,"remaining_time":0.0253301364},
{"learn":[3.090150687],"iteration":967,"passed_time":0.7429117907,"remaining_time":0.02455906746},
{"learn":[3.088612829],"iteration":968,"passed_time":0.7435431807,"remaining_time":0.02378724314},
{"learn":[3.087153684],"iteration":969,"passed_time":0.7441984221,"remaining_time":0.02301644605},
{"learn":[3.085866843],"iteration":970,"passed_time":0.7449399676,"remaining_time":0.02224846453},
{"learn":[3.082669094],"iteration":971,"passed_time":0.7460646236,"remaining_time":0.02149157352},
{"learn":[3.081047548],"iteration":972,"passed_time":0.7470618563,"remaining_time":0.02073039067},
{"learn":[3.079684322],"iteration":973,"passed_time":0.7478518671,"remaining_time":0.01996319152},
{"learn":[3.07613431],"iteration":974,"passed_time":0.74848476,"remaining_time":0.01919191692},
{"learn":[3.074005935],"iteration":975,"passed_time":0.749142502,"remaining_time":0.01842153693},
{"learn":[3.072988853],"iteration":976,"passed_time":0.7497891301,"remaining_time":0.01765112589},
{"learn":[3.072344268],"iteration":977,"passed_time":0.7504084369,"remaining_time":0.01688035339},
{"learn":[3.070654438],"iteration":978,"passed_time":0.7510506207,"remaining_time":0.01611038104},
{"learn":[3.069724506],"iteration":979,"passed_time":0.7516863322,"remaining_time":0.01534053739},
{"learn":[3.067763166],"iteration":980,"passed_time":0.752404377,"remaining_time":0.01457256184},
{"learn":[3.066737893],"iteration":981,"passed_time":0.7530977818,"remaining_time":0.01380423633},
{"learn":[3.065248174],"iteration":982,"passed_time":0.7538148629,"remaining_time":0.0130364727},
{"learn":[3.063186837],"iteration":983,"passed_time":0.7544968258,"remaining_time":0.01226824107},
{"learn":[3.062880371],"iteration":984,"passed_time":0.7552717547,"remaining_time":0.01150160033},
{"learn":[3.061288645],"iteration":985,"passed_time":0.7559663878,"remaining_time":0.01073380267},
{"learn":[3.059970575],"iteration":986,"passed_time":0.7565807941,"remaining_time":0.009965096579},
{"learn":[3.059576341],"iteration":987,"passed_time":0.7572652298,"remaining_time":0.009197553399},
{"learn":[3.058175919],"iteration":988,"passed_time":0.7579235265,"remaining_time":0.008429887555},
{"learn":[3.056830702],"iteration":989,"passed_time":0.7586914261,"remaining_time":0.007663549759},
{"learn":[3.056336579],"iteration":990,"passed_time":0.7593393536,"remaining_time":0.006896119256},
{"learn":[3.055810414],"iteration":991,"passed_time":0.7599756154,"remaining_time":0.006128835608},
{"learn":[3.055476518],"iteration":992,"passed_time":0.7608528911,"remaining_time":0.005363514842},
{"learn":[3.053331734],"iteration":993,"passed_time":0.7619363446,"remaining_time":0.004599213347},
{"learn":[3.050890374],"iteration":994,"passed_time":0.7628508471,"remaining_time":0.003833421342},
{"learn":[3.04972623],"iteration":995,"passed_time":0.7635524156,"remaining_time":0.003066475565},
{"learn":[3.047217327],"iteration":996,"passed_time":0.7643094208,"remaining_time":0.002299827746},
{"learn":[3.047155483],"iteration":997,"passed_time":0.7650479438,"remaining_time":0.001533162212},
{"learn":[3.04430671],"iteration":998,"passed_time":0.7659112377,"remaining_time":0.0007666779156},
{"learn":[3.042664195],"iteration":999,"passed_time":0.7666540598,"remaining_time":0}
]}